{"target": -1.4091751043333844, "params": {"model__colsample_bylevel": 0.999999998183932, "model__colsample_bynode": 0.3, "model__colsample_bytree": 0.35861461681034956, "model__learning_rate": 0.3, "model__max_depth": 4.0, "model__n_estimators": 29.0, "model__reg_lambda": 2.597475972619512}, "datetime": {"datetime": "2021-03-27 01:12:14", "elapsed": 0.0, "delta": 0.0}}
{"target": -1.4934725811070613, "params": {"model__colsample_bylevel": 0.3, "model__colsample_bynode": 1.0, "model__colsample_bytree": 0.3, "model__learning_rate": 0.3, "model__max_depth": 5.0, "model__n_estimators": 28.0, "model__reg_lambda": 2.445978412994987}, "datetime": {"datetime": "2021-03-27 01:12:14", "elapsed": 0.305876, "delta": 0.305876}}
{"target": -1.3763759732691816, "params": {"model__colsample_bylevel": 0.6310644289849315, "model__colsample_bynode": 0.3, "model__colsample_bytree": 1.0, "model__learning_rate": 0.3, "model__max_depth": 4.0, "model__n_estimators": 29.0, "model__reg_lambda": 8.127083395450825}, "datetime": {"datetime": "2021-03-27 01:12:14", "elapsed": 0.790045, "delta": 0.484169}}
{"target": -1.4086524154397027, "params": {"model__colsample_bylevel": 0.3, "model__colsample_bynode": 1.0, "model__colsample_bytree": 1.0, "model__learning_rate": 0.3, "model__max_depth": 2.0, "model__n_estimators": 26.0, "model__reg_lambda": 0.0}, "datetime": {"datetime": "2021-03-27 01:12:15", "elapsed": 1.15355, "delta": 0.363505}}
{"target": -1.4086524154397027, "params": {"model__colsample_bylevel": 0.3, "model__colsample_bynode": 1.0, "model__colsample_bytree": 1.0, "model__learning_rate": 0.3, "model__max_depth": 2.0, "model__n_estimators": 26.0, "model__reg_lambda": 0.0}, "datetime": {"datetime": "2021-03-27 01:12:15", "elapsed": 1.153849, "delta": 0.000299}}
{"target": -1.5806784517631152, "params": {"model__colsample_bylevel": 0.30726190771998996, "model__colsample_bynode": 0.651312214504117, "model__colsample_bytree": 0.6470413051939022, "model__learning_rate": 0.12676590579185532, "model__max_depth": 2.8526665127272315, "model__n_estimators": 18.278380134391174, "model__reg_lambda": 4.185081805104525}, "datetime": {"datetime": "2021-03-27 01:12:15", "elapsed": 1.38605, "delta": 0.232201}}
{"target": -1.3987395072976747, "params": {"model__colsample_bylevel": 0.4736708178894914, "model__colsample_bynode": 0.35884175581574507, "model__colsample_bytree": 0.54184904803528, "model__learning_rate": 0.1333552693064643, "model__max_depth": 7.271354513195954, "model__n_estimators": 29.26446047440075, "model__reg_lambda": 0.38748375832319826}, "datetime": {"datetime": "2021-03-27 01:12:15", "elapsed": 1.764977, "delta": 0.378927}}
{"target": -1.433689601421086, "params": {"model__colsample_bylevel": 0.7893751739791326, "model__colsample_bynode": 0.7009318708985864, "model__colsample_bytree": 0.9286049827576046, "model__learning_rate": 0.23337979458392732, "model__max_depth": 5.28702669827889, "model__n_estimators": 25.53641136102083, "model__reg_lambda": 3.864771696146654}, "datetime": {"datetime": "2021-03-27 01:12:16", "elapsed": 2.763034, "delta": 0.998057}}
{"target": -1.4295028312762768, "params": {"model__colsample_bylevel": 0.7861070744351207, "model__colsample_bynode": 0.8774093251503836, "model__colsample_bytree": 0.6259679327570861, "model__learning_rate": 0.28810488190533123, "model__max_depth": 6.822438620073907, "model__n_estimators": 29.75038872336499, "model__reg_lambda": 1.696362575837671}, "datetime": {"datetime": "2021-03-27 01:12:17", "elapsed": 3.641226, "delta": 0.878192}}
{"target": -1.4388429682229416, "params": {"model__colsample_bylevel": 0.6647592980218581, "model__colsample_bynode": 0.9618621918833685, "model__colsample_bytree": 0.7546783242123333, "model__learning_rate": 0.2721663846451393, "model__max_depth": 7.825076072541351, "model__n_estimators": 17.78312530401691, "model__reg_lambda": 2.431156753134085}, "datetime": {"datetime": "2021-03-27 01:12:18", "elapsed": 4.361692, "delta": 0.720466}}
{"target": -1.4779737598600164, "params": {"model__colsample_bylevel": 0.9113805901707872, "model__colsample_bynode": 0.9343940938464552, "model__colsample_bytree": 0.8307945907576542, "model__learning_rate": 0.16938039075510394, "model__max_depth": 4.781208283904345, "model__n_estimators": 24.15806611272194, "model__reg_lambda": 4.96281717671187}, "datetime": {"datetime": "2021-03-27 01:12:19", "elapsed": 5.623769, "delta": 1.262077}}
{"target": -1.5450021303866222, "params": {"model__colsample_bylevel": 0.6345818094768427, "model__colsample_bynode": 0.604888825336442, "model__colsample_bytree": 0.9092858074985717, "model__learning_rate": 0.1374717294122843, "model__max_depth": 6.126044559156051, "model__n_estimators": 25.552937607020823, "model__reg_lambda": 9.252000772711074}, "datetime": {"datetime": "2021-03-27 01:12:20", "elapsed": 6.454212, "delta": 0.830443}}
{"target": -1.5394981621508148, "params": {"model__colsample_bylevel": 0.32761837237198693, "model__colsample_bynode": 0.7529816994815779, "model__colsample_bytree": 0.7466377893021694, "model__learning_rate": 0.19233953249413938, "model__max_depth": 2.318356546912358, "model__n_estimators": 15.578563847435374, "model__reg_lambda": 1.6953141420787687}, "datetime": {"datetime": "2021-03-27 01:12:20", "elapsed": 6.663551, "delta": 0.209339}}
{"target": -1.4799143553859946, "params": {"model__colsample_bylevel": 0.8561835208849775, "model__colsample_bynode": 0.4138242325920566, "model__colsample_bytree": 0.3971170898456863, "model__learning_rate": 0.17058339064653638, "model__max_depth": 4.906990730916813, "model__n_estimators": 25.466045776856664, "model__reg_lambda": 8.011564316956859}, "datetime": {"datetime": "2021-03-27 01:12:21", "elapsed": 7.078793, "delta": 0.415242}}
{"target": -1.5062494180340698, "params": {"model__colsample_bylevel": 0.4867420639503589, "model__colsample_bynode": 0.936633346480775, "model__colsample_bytree": 0.3160068649787738, "model__learning_rate": 0.17502455249915477, "model__max_depth": 3.1977999718893484, "model__n_estimators": 20.142078437421155, "model__reg_lambda": 4.441122950440465}, "datetime": {"datetime": "2021-03-27 01:12:21", "elapsed": 7.336845, "delta": 0.258052}}
{"target": -1.492772481817266, "params": {"model__colsample_bylevel": 0.6486977272532548, "model__colsample_bynode": 0.5900424273597351, "model__colsample_bytree": 0.4499791740194562, "model__learning_rate": 0.14332794254537243, "model__max_depth": 3.3938427634789914, "model__n_estimators": 25.93628430939619, "model__reg_lambda": 4.159186670147922}, "datetime": {"datetime": "2021-03-27 01:12:21", "elapsed": 7.691805, "delta": 0.35496}}
{"target": -1.4667730124667286, "params": {"model__colsample_bylevel": 0.7087287246096596, "model__colsample_bynode": 0.6460356235928947, "model__colsample_bytree": 0.6010327699478305, "model__learning_rate": 0.24695316340723392, "model__max_depth": 5.337298920821893, "model__n_estimators": 19.539459624900097, "model__reg_lambda": 9.70798194813456}, "datetime": {"datetime": "2021-03-27 01:12:22", "elapsed": 8.208008, "delta": 0.516203}}
{"target": -1.5164296288583157, "params": {"model__colsample_bylevel": 0.4573898284863129, "model__colsample_bynode": 0.39713840986827087, "model__colsample_bytree": 0.730452732753553, "model__learning_rate": 0.19838578785694924, "model__max_depth": 3.0989164019193227, "model__n_estimators": 16.639657727470496, "model__reg_lambda": 5.395755249234239}, "datetime": {"datetime": "2021-03-27 01:12:22", "elapsed": 8.431939, "delta": 0.223931}}
{"target": -1.4008795747263492, "params": {"model__colsample_bylevel": 0.5025094970837707, "model__colsample_bynode": 0.37213783629228636, "model__colsample_bytree": 0.6434210837220209, "model__learning_rate": 0.22641833694649102, "model__max_depth": 2.227815301561689, "model__n_estimators": 22.50161880662639, "model__reg_lambda": 0.835434299294453}, "datetime": {"datetime": "2021-03-27 01:12:22", "elapsed": 8.664083, "delta": 0.232144}}
{"target": -1.4889767702236987, "params": {"model__colsample_bylevel": 0.8539227643210632, "model__colsample_bynode": 0.8306252174459399, "model__colsample_bytree": 0.4835912545620663, "model__learning_rate": 0.12017171820904433, "model__max_depth": 7.503156236962601, "model__n_estimators": 22.761903626532458, "model__reg_lambda": 1.3353967592343363}, "datetime": {"datetime": "2021-03-27 01:12:23", "elapsed": 9.386922, "delta": 0.722839}}
{"target": -1.5709092773875033, "params": {"model__colsample_bylevel": 0.3787801798303496, "model__colsample_bynode": 0.8891488038898538, "model__colsample_bytree": 0.682252315571295, "model__learning_rate": 0.1522033166295056, "model__max_depth": 5.4549531069191834, "model__n_estimators": 19.707789101668837, "model__reg_lambda": 7.916231853067416}, "datetime": {"datetime": "2021-03-27 01:12:23", "elapsed": 9.834822, "delta": 0.4479}}
{"target": -1.4251208110685476, "params": {"model__colsample_bylevel": 0.6451635028820711, "model__colsample_bynode": 0.9756107284220326, "model__colsample_bytree": 0.6642183611480073, "model__learning_rate": 0.2806043190994539, "model__max_depth": 3.4988273636139016, "model__n_estimators": 22.822309547759104, "model__reg_lambda": 5.0574568339000425}, "datetime": {"datetime": "2021-03-27 01:12:24", "elapsed": 10.408879, "delta": 0.574057}}
{"target": -1.5038752020269202, "params": {"model__colsample_bylevel": 0.8691500365097846, "model__colsample_bynode": 0.35123595486158105, "model__colsample_bytree": 0.8853449005213216, "model__learning_rate": 0.26084712707576596, "model__max_depth": 4.4379276251183954, "model__n_estimators": 15.546768724832507, "model__reg_lambda": 7.672541069525759}, "datetime": {"datetime": "2021-03-27 01:12:24", "elapsed": 10.792092, "delta": 0.383213}}
{"target": -1.432882422408548, "params": {"model__colsample_bylevel": 0.7752492983214213, "model__colsample_bynode": 0.9432502217801924, "model__colsample_bytree": 0.6921299356114399, "model__learning_rate": 0.2935437919451478, "model__max_depth": 3.850306106454099, "model__n_estimators": 20.083349491730285, "model__reg_lambda": 7.308818114469667}, "datetime": {"datetime": "2021-03-27 01:12:25", "elapsed": 11.527539, "delta": 0.735447}}
{"target": -1.4377250128169206, "params": {"model__colsample_bylevel": 0.7909589341540182, "model__colsample_bynode": 0.8077442453063763, "model__colsample_bytree": 0.9257599208468199, "model__learning_rate": 0.24332981747869467, "model__max_depth": 6.092916621028417, "model__n_estimators": 27.646752630781677, "model__reg_lambda": 6.451189984951728}, "datetime": {"datetime": "2021-03-27 01:12:26", "elapsed": 12.784012, "delta": 1.256473}}
{"target": -1.4322491875269274, "params": {"model__colsample_bylevel": 0.511889221690131, "model__colsample_bynode": 0.880146841574702, "model__colsample_bytree": 0.4713036833734444, "model__learning_rate": 0.24075613859849618, "model__max_depth": 5.215329445061823, "model__n_estimators": 20.712142781227694, "model__reg_lambda": 1.7861793515885238}, "datetime": {"datetime": "2021-03-27 01:12:27", "elapsed": 13.200085, "delta": 0.416073}}
{"target": -1.4059880383083245, "params": {"model__colsample_bylevel": 0.9200821231031391, "model__colsample_bynode": 0.35616344543935075, "model__colsample_bytree": 0.8625120529528605, "model__learning_rate": 0.23669407037870885, "model__max_depth": 4.772062647788025, "model__n_estimators": 24.96073964162097, "model__reg_lambda": 2.826662622956666}, "datetime": {"datetime": "2021-03-27 01:12:27", "elapsed": 13.814841, "delta": 0.614756}}
{"target": -1.5152899846110655, "params": {"model__colsample_bylevel": 0.9031023424555509, "model__colsample_bynode": 0.4249356891249156, "model__colsample_bytree": 0.7057975471157624, "model__learning_rate": 0.1927268764937271, "model__max_depth": 6.039330960316078, "model__n_estimators": 22.141866816168736, "model__reg_lambda": 9.525111535091707}, "datetime": {"datetime": "2021-03-27 01:12:28", "elapsed": 14.396726, "delta": 0.581885}}
{"target": -1.4897658898670605, "params": {"model__colsample_bylevel": 0.8972803412913453, "model__colsample_bynode": 0.9289549741797964, "model__colsample_bytree": 0.3178983723326505, "model__learning_rate": 0.13128458043568686, "model__max_depth": 4.861388901041763, "model__n_estimators": 26.020827615199973, "model__reg_lambda": 3.5630947732495777}, "datetime": {"datetime": "2021-03-27 01:12:29", "elapsed": 15.014988, "delta": 0.618262}}
{"target": -1.4809184664050519, "params": {"model__colsample_bylevel": 0.6951175428742368, "model__colsample_bynode": 0.3318286487069968, "model__colsample_bytree": 0.7483089139197432, "model__learning_rate": 0.23624127616156612, "model__max_depth": 4.373824850662889, "model__n_estimators": 17.05009515507337, "model__reg_lambda": 4.16457752159582}, "datetime": {"datetime": "2021-03-27 01:12:29", "elapsed": 15.317854, "delta": 0.302866}}
{"target": -1.4675073876160372, "params": {"model__colsample_bylevel": 0.816923983909474, "model__colsample_bynode": 0.7090153450298311, "model__colsample_bytree": 0.9184032582594783, "model__learning_rate": 0.21574992226411746, "model__max_depth": 3.0678227617515392, "model__n_estimators": 23.876275396014634, "model__reg_lambda": 0.5387774367636355}, "datetime": {"datetime": "2021-03-27 01:12:30", "elapsed": 16.034386, "delta": 0.716532}}
{"target": -1.567692979414394, "params": {"model__colsample_bylevel": 0.8203891930140093, "model__colsample_bynode": 0.4407263630351047, "model__colsample_bytree": 0.9332727397304375, "model__learning_rate": 0.19471357604823214, "model__max_depth": 4.649919104965563, "model__n_estimators": 17.041195531585494, "model__reg_lambda": 8.076955975507973}, "datetime": {"datetime": "2021-03-27 01:12:30", "elapsed": 16.553506, "delta": 0.51912}}
{"target": -1.4541988320594679, "params": {"model__colsample_bylevel": 0.941920130237188, "model__colsample_bynode": 0.7862119444399247, "model__colsample_bytree": 0.7672811212479322, "model__learning_rate": 0.2413235529719557, "model__max_depth": 6.468881607544759, "model__n_estimators": 25.71892738561766, "model__reg_lambda": 1.4296252407525012}, "datetime": {"datetime": "2021-03-27 01:12:31", "elapsed": 17.601634, "delta": 1.048128}}
{"target": -1.5909347063713315, "params": {"model__colsample_bylevel": 0.7664505634998717, "model__colsample_bynode": 0.9372501752435591, "model__colsample_bytree": 0.3226974712037688, "model__learning_rate": 0.13696287496610304, "model__max_depth": 6.574112506330284, "model__n_estimators": 15.628001246231364, "model__reg_lambda": 2.789864730302046}, "datetime": {"datetime": "2021-03-27 01:12:32", "elapsed": 18.001434, "delta": 0.3998}}
{"target": -1.5909315695581228, "params": {"model__colsample_bylevel": 0.9005722896485118, "model__colsample_bynode": 0.5583279975276154, "model__colsample_bytree": 0.9292943127471143, "model__learning_rate": 0.1578195662504995, "model__max_depth": 4.281940885644073, "model__n_estimators": 16.640600890305116, "model__reg_lambda": 8.146246111896012}, "datetime": {"datetime": "2021-03-27 01:12:32", "elapsed": 18.608651, "delta": 0.607217}}
{"target": -1.507793735674974, "params": {"model__colsample_bylevel": 0.9534398095322711, "model__colsample_bynode": 0.42817503247553923, "model__colsample_bytree": 0.5178389967922328, "model__learning_rate": 0.2349408086546986, "model__max_depth": 2.4746062530577846, "model__n_estimators": 15.490859914517099, "model__reg_lambda": 3.2657561880327557}, "datetime": {"datetime": "2021-03-27 01:12:32", "elapsed": 18.812213, "delta": 0.203562}}
{"target": -1.4837185490714468, "params": {"model__colsample_bylevel": 0.5706285360217014, "model__colsample_bynode": 0.6842771415696982, "model__colsample_bytree": 0.6870518207102555, "model__learning_rate": 0.16602543474194267, "model__max_depth": 4.553906607318516, "model__n_estimators": 18.777852885612205, "model__reg_lambda": 2.0263513230551347}, "datetime": {"datetime": "2021-03-27 01:12:33", "elapsed": 19.289635, "delta": 0.477422}}
{"target": -1.431356358026033, "params": {"model__colsample_bylevel": 0.8442678591461368, "model__colsample_bynode": 0.3977149946980818, "model__colsample_bytree": 0.6158425941754111, "model__learning_rate": 0.1245045248421828, "model__max_depth": 6.897715409068526, "model__n_estimators": 27.65234893164894, "model__reg_lambda": 1.1477505735172433}, "datetime": {"datetime": "2021-03-27 01:12:34", "elapsed": 19.902276, "delta": 0.612641}}
{"target": -1.5067027705195157, "params": {"model__colsample_bylevel": 0.8046871964072875, "model__colsample_bynode": 0.9463208373893632, "model__colsample_bytree": 0.5702216525068842, "model__learning_rate": 0.25542256115422385, "model__max_depth": 7.543314227663024, "model__n_estimators": 15.074271146872483, "model__reg_lambda": 2.7258381373747875}, "datetime": {"datetime": "2021-03-27 01:12:34", "elapsed": 20.48303, "delta": 0.580754}}
{"target": -1.7101605852552946, "params": {"model__colsample_bylevel": 0.325563385911891, "model__colsample_bynode": 0.4394342284138872, "model__colsample_bytree": 0.3078454924320954, "model__learning_rate": 0.10977990666788635, "model__max_depth": 5.896055639118223, "model__n_estimators": 19.33085301818661, "model__reg_lambda": 8.44410233607059}, "datetime": {"datetime": "2021-03-27 01:12:34", "elapsed": 20.689382, "delta": 0.206352}}
{"target": -1.4130946476201434, "params": {"model__colsample_bylevel": 0.5333078077907257, "model__colsample_bynode": 0.9449148964303926, "model__colsample_bytree": 0.39197068792833056, "model__learning_rate": 0.2098009976534188, "model__max_depth": 3.7666070082368948, "model__n_estimators": 27.09229802758709, "model__reg_lambda": 3.376766038812906}, "datetime": {"datetime": "2021-03-27 01:12:35", "elapsed": 21.144113, "delta": 0.454731}}
{"target": -1.4463349235810985, "params": {"model__colsample_bylevel": 0.38472058045866103, "model__colsample_bynode": 0.6189182754661343, "model__colsample_bytree": 0.47491716651278293, "model__learning_rate": 0.24904662090967875, "model__max_depth": 6.41552028192452, "model__n_estimators": 15.15307284998927, "model__reg_lambda": 0.029919695529196932}, "datetime": {"datetime": "2021-03-27 01:12:35", "elapsed": 21.384185, "delta": 0.240072}}
{"target": -1.4228052763322343, "params": {"model__colsample_bylevel": 0.9426044924017256, "model__colsample_bynode": 0.5260125425777793, "model__colsample_bytree": 0.5074653319167783, "model__learning_rate": 0.15418522802672452, "model__max_depth": 3.474343666196627, "model__n_estimators": 26.630539663467353, "model__reg_lambda": 2.632384799456182}, "datetime": {"datetime": "2021-03-27 01:12:35", "elapsed": 21.849446, "delta": 0.465261}}
{"target": -1.4533363601381795, "params": {"model__colsample_bylevel": 0.8032909797610204, "model__colsample_bynode": 0.7713021432027297, "model__colsample_bytree": 0.6853736563856032, "model__learning_rate": 0.23655460523720243, "model__max_depth": 3.0441975506001606, "model__n_estimators": 21.967771044500967, "model__reg_lambda": 4.939589109277965}, "datetime": {"datetime": "2021-03-27 01:12:36", "elapsed": 22.419378, "delta": 0.569932}}
{"target": -1.4657185439965217, "params": {"model__colsample_bylevel": 0.3191878877624776, "model__colsample_bynode": 0.4527668367686508, "model__colsample_bytree": 0.9533861738476699, "model__learning_rate": 0.23172885748318614, "model__max_depth": 7.871974941466348, "model__n_estimators": 20.539710627919593, "model__reg_lambda": 7.6239037960184355}, "datetime": {"datetime": "2021-03-27 01:12:36", "elapsed": 22.791379, "delta": 0.372001}}
{"target": -1.5495891640691652, "params": {"model__colsample_bylevel": 0.7197656118669662, "model__colsample_bynode": 0.7214646750503465, "model__colsample_bytree": 0.37931534877147977, "model__learning_rate": 0.14444015703665763, "model__max_depth": 2.433575141809544, "model__n_estimators": 22.57954207818872, "model__reg_lambda": 3.4509917372173025}, "datetime": {"datetime": "2021-03-27 01:12:37", "elapsed": 23.06023, "delta": 0.268851}}
{"target": -1.4273378387876394, "params": {"model__colsample_bylevel": 0.43770438267170664, "model__colsample_bynode": 0.562288016838024, "model__colsample_bytree": 0.6684847059501842, "model__learning_rate": 0.24216538663414655, "model__max_depth": 5.53982800385271, "model__n_estimators": 24.586364893849456, "model__reg_lambda": 6.03761911116279}, "datetime": {"datetime": "2021-03-27 01:12:37", "elapsed": 23.504166, "delta": 0.443936}}
{"target": -1.4276174399380883, "params": {"model__colsample_bylevel": 0.5615024327662378, "model__colsample_bynode": 0.5278880157630303, "model__colsample_bytree": 0.6927994632423486, "model__learning_rate": 0.2499326997232081, "model__max_depth": 7.515144966264312, "model__n_estimators": 27.41503748405572, "model__reg_lambda": 5.537273620404508}, "datetime": {"datetime": "2021-03-27 01:12:38", "elapsed": 24.060532, "delta": 0.556366}}
{"target": -1.4535776109502152, "params": {"model__colsample_bylevel": 0.8773753442334304, "model__colsample_bynode": 0.3197624374107063, "model__colsample_bytree": 0.8582648079772404, "model__learning_rate": 0.1398977410305498, "model__max_depth": 6.115045756510598, "model__n_estimators": 27.377846347953547, "model__reg_lambda": 3.1496308071503187}, "datetime": {"datetime": "2021-03-27 01:12:38", "elapsed": 24.708944, "delta": 0.648412}}
{"target": -1.4822146198860762, "params": {"model__colsample_bylevel": 0.5798231824380045, "model__colsample_bynode": 0.9899122285696411, "model__colsample_bytree": 0.4774952834387126, "model__learning_rate": 0.25106786479472265, "model__max_depth": 4.436357453829759, "model__n_estimators": 19.72844903945682, "model__reg_lambda": 7.705159221072094}, "datetime": {"datetime": "2021-03-27 01:12:39", "elapsed": 25.153886, "delta": 0.444942}}
{"target": -1.4660800366190032, "params": {"model__colsample_bylevel": 0.6149024037576569, "model__colsample_bynode": 0.7970601762740899, "model__colsample_bytree": 0.4555403075808654, "model__learning_rate": 0.26476738246878556, "model__max_depth": 6.3006447069266285, "model__n_estimators": 22.48861984031197, "model__reg_lambda": 7.91551010046181}, "datetime": {"datetime": "2021-03-27 01:12:39", "elapsed": 25.664162, "delta": 0.510276}}
{"target": -1.4145681399501104, "params": {"model__colsample_bylevel": 0.9437937215686736, "model__colsample_bynode": 0.8511722448868555, "model__colsample_bytree": 0.5084857837350747, "model__learning_rate": 0.24346701302396254, "model__max_depth": 5.690340786662006, "model__n_estimators": 27.619845335231588, "model__reg_lambda": 4.0456797253845265}, "datetime": {"datetime": "2021-03-27 01:12:40", "elapsed": 26.571251, "delta": 0.907089}}
{"target": -1.4400901399390853, "params": {"model__colsample_bylevel": 0.6173529449301774, "model__colsample_bynode": 0.3656352091501882, "model__colsample_bytree": 0.45305055880659917, "model__learning_rate": 0.20586849821836273, "model__max_depth": 5.173197962934258, "model__n_estimators": 25.696146745858105, "model__reg_lambda": 2.863925264426952}, "datetime": {"datetime": "2021-03-27 01:12:41", "elapsed": 26.914696, "delta": 0.343445}}
{"target": -1.5764826857309413, "params": {"model__colsample_bylevel": 0.3812502817792496, "model__colsample_bynode": 0.43107613084910207, "model__colsample_bytree": 0.6036033759584388, "model__learning_rate": 0.13710847453713484, "model__max_depth": 2.7407946095138094, "model__n_estimators": 25.875381462387566, "model__reg_lambda": 9.101677556132595}, "datetime": {"datetime": "2021-03-27 01:12:41", "elapsed": 27.179111, "delta": 0.264415}}
{"target": -1.4516993045482944, "params": {"model__colsample_bylevel": 0.3426383940311504, "model__colsample_bynode": 0.3292770968669983, "model__colsample_bytree": 0.49999974247633633, "model__learning_rate": 0.21592871225493404, "model__max_depth": 7.629568478689846, "model__n_estimators": 23.72527860523467, "model__reg_lambda": 6.7998375849329875}, "datetime": {"datetime": "2021-03-27 01:12:41", "elapsed": 27.44695, "delta": 0.267839}}
{"target": -1.4390923539014615, "params": {"model__colsample_bylevel": 1.0, "model__colsample_bynode": 0.3, "model__colsample_bytree": 0.3, "model__learning_rate": 0.3, "model__max_depth": 8.0, "model__n_estimators": 30.0, "model__reg_lambda": 10.0}, "datetime": {"datetime": "2021-03-27 01:12:42", "elapsed": 28.387022, "delta": 0.940072}}
{"target": -1.5274940935138992, "params": {"model__colsample_bylevel": 1.0, "model__colsample_bynode": 1.0, "model__colsample_bytree": 1.0, "model__learning_rate": 0.3, "model__max_depth": 8.0, "model__n_estimators": 15.0, "model__reg_lambda": 10.0}, "datetime": {"datetime": "2021-03-27 01:12:44", "elapsed": 30.121494, "delta": 1.734472}}
{"target": -1.4545736032659593, "params": {"model__colsample_bylevel": 1.0, "model__colsample_bynode": 1.0, "model__colsample_bytree": 0.3, "model__learning_rate": 0.3, "model__max_depth": 2.0, "model__n_estimators": 30.0, "model__reg_lambda": 10.0}, "datetime": {"datetime": "2021-03-27 01:12:45", "elapsed": 31.211329, "delta": 1.089835}}
{"target": -1.460833415850673, "params": {"model__colsample_bylevel": 1.0, "model__colsample_bynode": 1.0, "model__colsample_bytree": 1.0, "model__learning_rate": 0.3, "model__max_depth": 2.0, "model__n_estimators": 30.0, "model__reg_lambda": 5.228730956928879}, "datetime": {"datetime": "2021-03-27 01:12:46", "elapsed": 32.820535, "delta": 1.609206}}
{"target": -1.442416570826933, "params": {"model__colsample_bylevel": 1.0, "model__colsample_bynode": 0.3, "model__colsample_bytree": 1.0, "model__learning_rate": 0.3, "model__max_depth": 8.0, "model__n_estimators": 19.3726049417607, "model__reg_lambda": 0.0}, "datetime": {"datetime": "2021-03-27 01:12:48", "elapsed": 33.982158, "delta": 1.161623}}
{"target": -1.4933068261090394, "params": {"model__colsample_bylevel": 0.3, "model__colsample_bynode": 1.0, "model__colsample_bytree": 1.0, "model__learning_rate": 0.3, "model__max_depth": 2.0, "model__n_estimators": 20.306037339287418, "model__reg_lambda": 10.0}, "datetime": {"datetime": "2021-03-27 01:12:49", "elapsed": 35.013513, "delta": 1.031355}}
{"target": -1.3678425127005986, "params": {"model__colsample_bylevel": 1.0, "model__colsample_bynode": 0.3, "model__colsample_bytree": 0.3, "model__learning_rate": 0.3, "model__max_depth": 2.0, "model__n_estimators": 30.0, "model__reg_lambda": 0.0}, "datetime": {"datetime": "2021-03-27 01:12:50", "elapsed": 35.943481, "delta": 0.929968}}
{"target": -1.4027472871598667, "params": {"model__colsample_bylevel": 1.0, "model__colsample_bynode": 0.3, "model__colsample_bytree": 1.0, "model__learning_rate": 0.3, "model__max_depth": 8.0, "model__n_estimators": 21.212285638926666, "model__reg_lambda": 4.159418689937161}, "datetime": {"datetime": "2021-03-27 01:12:51", "elapsed": 37.256804, "delta": 1.313323}}
{"target": -1.413575608159105, "params": {"model__colsample_bylevel": 0.3, "model__colsample_bynode": 0.3, "model__colsample_bytree": 1.0, "model__learning_rate": 0.3, "model__max_depth": 2.0, "model__n_estimators": 19.18350313138558, "model__reg_lambda": 0.0}, "datetime": {"datetime": "2021-03-27 01:12:52", "elapsed": 38.197827, "delta": 0.941023}}
{"target": -1.4614367422286718, "params": {"model__colsample_bylevel": 0.3, "model__colsample_bynode": 0.3, "model__colsample_bytree": 1.0, "model__learning_rate": 0.3, "model__max_depth": 8.0, "model__n_estimators": 25.306078234654926, "model__reg_lambda": 0.0}, "datetime": {"datetime": "2021-03-27 01:12:53", "elapsed": 39.357529, "delta": 1.159702}}
{"target": -1.4336080389124328, "params": {"model__colsample_bylevel": 1.0, "model__colsample_bynode": 0.3, "model__colsample_bytree": 0.3, "model__learning_rate": 0.3, "model__max_depth": 8.0, "model__n_estimators": 30.0, "model__reg_lambda": 5.050274719075401}, "datetime": {"datetime": "2021-03-27 01:12:54", "elapsed": 40.484734, "delta": 1.127205}}
{"target": -1.5697188467015109, "params": {"model__colsample_bylevel": 1.0, "model__colsample_bynode": 1.0, "model__colsample_bytree": 1.0, "model__learning_rate": 0.3, "model__max_depth": 8.0, "model__n_estimators": 30.0, "model__reg_lambda": 0.0}, "datetime": {"datetime": "2021-03-27 01:12:56", "elapsed": 42.77739, "delta": 2.292656}}
{"target": -1.5037924073312594, "params": {"model__colsample_bylevel": 0.3, "model__colsample_bynode": 0.3, "model__colsample_bytree": 0.3, "model__learning_rate": 0.3, "model__max_depth": 4.962647782860526, "model__n_estimators": 30.0, "model__reg_lambda": 10.0}, "datetime": {"datetime": "2021-03-27 01:12:57", "elapsed": 43.808056, "delta": 1.030666}}
{"target": -1.504020713844701, "params": {"model__colsample_bylevel": 0.3, "model__colsample_bynode": 0.3, "model__colsample_bytree": 0.3, "model__learning_rate": 0.3, "model__max_depth": 2.0, "model__n_estimators": 27.56438641289172, "model__reg_lambda": 0.0}, "datetime": {"datetime": "2021-03-27 01:12:58", "elapsed": 44.662295, "delta": 0.854239}}
{"target": -1.4246224212905636, "params": {"model__colsample_bylevel": 1.0, "model__colsample_bynode": 1.0, "model__colsample_bytree": 0.3, "model__learning_rate": 0.3, "model__max_depth": 4.25877998305279, "model__n_estimators": 30.0, "model__reg_lambda": 7.3122840797562265}, "datetime": {"datetime": "2021-03-27 01:13:00", "elapsed": 46.139646, "delta": 1.477351}}
{"target": -1.4485552588558714, "params": {"model__colsample_bylevel": 1.0, "model__colsample_bynode": 0.3, "model__colsample_bytree": 1.0, "model__learning_rate": 0.3, "model__max_depth": 4.561832119786244, "model__n_estimators": 30.0, "model__reg_lambda": 0.0}, "datetime": {"datetime": "2021-03-27 01:13:01", "elapsed": 47.468833, "delta": 1.329187}}
{"target": -1.471735671437953, "params": {"model__colsample_bylevel": 1.0, "model__colsample_bynode": 1.0, "model__colsample_bytree": 1.0, "model__learning_rate": 0.3, "model__max_depth": 8.0, "model__n_estimators": 20.506834670857693, "model__reg_lambda": 10.0}, "datetime": {"datetime": "2021-03-27 01:13:03", "elapsed": 49.71737, "delta": 2.248537}}
{"target": -1.597071286647216, "params": {"model__colsample_bylevel": 0.3, "model__colsample_bynode": 0.3, "model__colsample_bytree": 1.0, "model__learning_rate": 0.3, "model__max_depth": 2.0, "model__n_estimators": 15.0, "model__reg_lambda": 10.0}, "datetime": {"datetime": "2021-03-27 01:13:04", "elapsed": 50.645102, "delta": 0.927732}}
{"target": -1.5111067319558797, "params": {"model__colsample_bylevel": 0.3, "model__colsample_bynode": 0.3, "model__colsample_bytree": 1.0, "model__learning_rate": 0.3, "model__max_depth": 8.0, "model__n_estimators": 15.0, "model__reg_lambda": 5.742337861298339}, "datetime": {"datetime": "2021-03-27 01:13:05", "elapsed": 51.641286, "delta": 0.996184}}
{"target": -1.5033568595009654, "params": {"model__colsample_bylevel": 1.0, "model__colsample_bynode": 0.3, "model__colsample_bytree": 0.3, "model__learning_rate": 0.3, "model__max_depth": 8.0, "model__n_estimators": 15.0, "model__reg_lambda": 0.0}, "datetime": {"datetime": "2021-03-27 01:13:06", "elapsed": 52.576894, "delta": 0.935608}}
{"target": -1.4633699721764721, "params": {"model__colsample_bylevel": 0.3, "model__colsample_bynode": 0.3, "model__colsample_bytree": 1.0, "model__learning_rate": 0.3, "model__max_depth": 5.124146792409113, "model__n_estimators": 21.572235809374842, "model__reg_lambda": 3.673759397960365}, "datetime": {"datetime": "2021-03-27 01:13:07", "elapsed": 53.752724, "delta": 1.17583}}
{"target": -1.4613389950367095, "params": {"model__colsample_bylevel": 1.0, "model__colsample_bynode": 1.0, "model__colsample_bytree": 0.3, "model__learning_rate": 0.3, "model__max_depth": 2.0, "model__n_estimators": 20.96652850915962, "model__reg_lambda": 0.0}, "datetime": {"datetime": "2021-03-27 01:13:09", "elapsed": 54.930092, "delta": 1.177368}}
{"target": -1.3653675598686263, "params": {"model__colsample_bylevel": 1.0, "model__colsample_bynode": 0.3, "model__colsample_bytree": 1.0, "model__learning_rate": 0.3, "model__max_depth": 2.0, "model__n_estimators": 30.0, "model__reg_lambda": 1.64551885384336}, "datetime": {"datetime": "2021-03-27 01:13:10", "elapsed": 56.159495, "delta": 1.229403}}
{"target": -1.468449432444691, "params": {"model__colsample_bylevel": 1.0, "model__colsample_bynode": 0.3, "model__colsample_bytree": 1.0, "model__learning_rate": 0.3, "model__max_depth": 3.796106875282789, "model__n_estimators": 15.0, "model__reg_lambda": 0.0}, "datetime": {"datetime": "2021-03-27 01:13:11", "elapsed": 57.270026, "delta": 1.110531}}
{"target": -1.452670001608414, "params": {"model__colsample_bylevel": 0.3, "model__colsample_bynode": 1.0, "model__colsample_bytree": 1.0, "model__learning_rate": 0.3, "model__max_depth": 4.049275611293996, "model__n_estimators": 15.0, "model__reg_lambda": 4.607172540865321}, "datetime": {"datetime": "2021-03-27 01:13:12", "elapsed": 58.520107, "delta": 1.250081}}
{"target": -1.464504232487061, "params": {"model__colsample_bylevel": 1.0, "model__colsample_bynode": 1.0, "model__colsample_bytree": 1.0, "model__learning_rate": 0.3, "model__max_depth": 3.6957591565822074, "model__n_estimators": 22.120210952888716, "model__reg_lambda": 10.0}, "datetime": {"datetime": "2021-03-27 01:13:14", "elapsed": 60.804687, "delta": 2.28458}}
{"target": -1.4877012355158619, "params": {"model__colsample_bylevel": 0.3, "model__colsample_bynode": 0.3, "model__colsample_bytree": 0.3, "model__learning_rate": 0.3, "model__max_depth": 4.6860070048100955, "model__n_estimators": 20.308405285261976, "model__reg_lambda": 0.0}, "datetime": {"datetime": "2021-03-27 01:13:15", "elapsed": 61.748715, "delta": 0.944028}}
{"target": -1.554323721245147, "params": {"model__colsample_bylevel": 0.3, "model__colsample_bynode": 0.3, "model__colsample_bytree": 0.3, "model__learning_rate": 0.3, "model__max_depth": 2.0, "model__n_estimators": 30.0, "model__reg_lambda": 7.742396817873377}, "datetime": {"datetime": "2021-03-27 01:13:16", "elapsed": 62.781277, "delta": 1.032562}}
{"target": -1.4934315822087227, "params": {"model__colsample_bylevel": 0.3, "model__colsample_bynode": 0.3, "model__colsample_bytree": 0.3, "model__learning_rate": 0.3, "model__max_depth": 8.0, "model__n_estimators": 28.46198065345184, "model__reg_lambda": 2.014726203409831}, "datetime": {"datetime": "2021-03-27 01:13:17", "elapsed": 63.847672, "delta": 1.066395}}
{"target": -1.4726261619937377, "params": {"model__colsample_bylevel": 1.0, "model__colsample_bynode": 1.0, "model__colsample_bytree": 1.0, "model__learning_rate": 0.3, "model__max_depth": 8.0, "model__n_estimators": 18.986262632447804, "model__reg_lambda": 5.78207468975527}, "datetime": {"datetime": "2021-03-27 01:13:20", "elapsed": 66.107337, "delta": 2.259665}}
{"target": -1.464554991358486, "params": {"model__colsample_bylevel": 0.3, "model__colsample_bynode": 0.3, "model__colsample_bytree": 1.0, "model__learning_rate": 0.3, "model__max_depth": 8.0, "model__n_estimators": 15.0, "model__reg_lambda": 1.0312402205472153}, "datetime": {"datetime": "2021-03-27 01:13:21", "elapsed": 67.128872, "delta": 1.021535}}
{"target": -1.4225474004917171, "params": {"model__colsample_bylevel": 1.0, "model__colsample_bynode": 0.3, "model__colsample_bytree": 1.0, "model__learning_rate": 0.3, "model__max_depth": 8.0, "model__n_estimators": 30.0, "model__reg_lambda": 7.974022525218575}, "datetime": {"datetime": "2021-03-27 01:13:23", "elapsed": 68.881191, "delta": 1.752319}}
{"target": -1.4442315691164223, "params": {"model__colsample_bylevel": 0.3, "model__colsample_bynode": 1.0, "model__colsample_bytree": 1.0, "model__learning_rate": 0.3, "model__max_depth": 8.0, "model__n_estimators": 17.141594143940466, "model__reg_lambda": 0.0}, "datetime": {"datetime": "2021-03-27 01:13:24", "elapsed": 70.248395, "delta": 1.367204}}
{"target": -1.4935741437356111, "params": {"model__colsample_bylevel": 0.3, "model__colsample_bynode": 1.0, "model__colsample_bytree": 1.0, "model__learning_rate": 0.1, "model__max_depth": 2.0, "model__n_estimators": 30.0, "model__reg_lambda": 0.0}, "datetime": {"datetime": "2021-03-27 01:13:25", "elapsed": 71.420989, "delta": 1.172594}}
{"target": -1.4164322905417912, "params": {"model__colsample_bylevel": 1.0, "model__colsample_bynode": 0.3, "model__colsample_bytree": 1.0, "model__learning_rate": 0.3, "model__max_depth": 5.0502591839792865, "model__n_estimators": 30.0, "model__reg_lambda": 5.096608303720065}, "datetime": {"datetime": "2021-03-27 01:13:27", "elapsed": 72.993443, "delta": 1.572454}}
{"target": -1.4170040179435432, "params": {"model__colsample_bylevel": 0.3, "model__colsample_bynode": 1.0, "model__colsample_bytree": 1.0, "model__learning_rate": 0.3, "model__max_depth": 8.0, "model__n_estimators": 20.50207956844426, "model__reg_lambda": 1.8195591296830353}, "datetime": {"datetime": "2021-03-27 01:13:28", "elapsed": 74.499062, "delta": 1.505619}}
{"target": -1.445515789900083, "params": {"model__colsample_bylevel": 1.0, "model__colsample_bynode": 1.0, "model__colsample_bytree": 1.0, "model__learning_rate": 0.3, "model__max_depth": 8.0, "model__n_estimators": 22.535274043852922, "model__reg_lambda": 6.700650342525558}, "datetime": {"datetime": "2021-03-27 01:13:31", "elapsed": 77.018689, "delta": 2.519627}}
{"target": -1.4173282733686485, "params": {"model__colsample_bylevel": 0.3, "model__colsample_bynode": 1.0, "model__colsample_bytree": 1.0, "model__learning_rate": 0.3, "model__max_depth": 2.0, "model__n_estimators": 21.827871103254747, "model__reg_lambda": 0.0}, "datetime": {"datetime": "2021-03-27 01:13:32", "elapsed": 78.104154, "delta": 1.085465}}
{"target": -1.4426564198176282, "params": {"model__colsample_bylevel": 1.0, "model__colsample_bynode": 0.3, "model__colsample_bytree": 0.3, "model__learning_rate": 0.3, "model__max_depth": 8.0, "model__n_estimators": 27.552606313160293, "model__reg_lambda": 8.262163688771455}, "datetime": {"datetime": "2021-03-27 01:13:33", "elapsed": 79.445668, "delta": 1.341514}}
{"target": -1.4052685233426916, "params": {"model__colsample_bylevel": 1.0, "model__colsample_bynode": 1.0, "model__colsample_bytree": 0.3, "model__learning_rate": 0.3, "model__max_depth": 2.0, "model__n_estimators": 30.0, "model__reg_lambda": 1.8981041420312033}, "datetime": {"datetime": "2021-03-27 01:13:35", "elapsed": 80.916473, "delta": 1.470805}}
{"target": -1.4743372126198981, "params": {"model__colsample_bylevel": 1.0, "model__colsample_bynode": 1.0, "model__colsample_bytree": 1.0, "model__learning_rate": 0.3, "model__max_depth": 2.0, "model__n_estimators": 27.483362937767076, "model__reg_lambda": 3.0396240979413367}, "datetime": {"datetime": "2021-03-27 01:13:36", "elapsed": 82.814171, "delta": 1.897698}}
{"target": -1.6066102330775365, "params": {"model__colsample_bylevel": 0.3, "model__colsample_bynode": 0.3, "model__colsample_bytree": 0.3, "model__learning_rate": 0.3, "model__max_depth": 2.0, "model__n_estimators": 15.0, "model__reg_lambda": 0.0}, "datetime": {"datetime": "2021-03-27 01:13:37", "elapsed": 83.665904, "delta": 0.851733}}
{"target": -1.4372612792080726, "params": {"model__colsample_bylevel": 0.3, "model__colsample_bynode": 0.3, "model__colsample_bytree": 1.0, "model__learning_rate": 0.3, "model__max_depth": 2.0, "model__n_estimators": 24.880522753222067, "model__reg_lambda": 1.1706885981843191}, "datetime": {"datetime": "2021-03-27 01:13:39", "elapsed": 85.32908, "delta": 1.663176}}
{"target": -1.4165122629021822, "params": {"model__colsample_bylevel": 0.3, "model__colsample_bynode": 1.0, "model__colsample_bytree": 1.0, "model__learning_rate": 0.3, "model__max_depth": 8.0, "model__n_estimators": 30.0, "model__reg_lambda": 10.0}, "datetime": {"datetime": "2021-03-27 01:13:41", "elapsed": 87.624018, "delta": 2.294938}}
{"target": -1.5639926985155899, "params": {"model__colsample_bylevel": 1.0, "model__colsample_bynode": 1.0, "model__colsample_bytree": 1.0, "model__learning_rate": 0.3, "model__max_depth": 6.76499866949438, "model__n_estimators": 15.0, "model__reg_lambda": 0.0}, "datetime": {"datetime": "2021-03-27 01:13:44", "elapsed": 90.365302, "delta": 2.741284}}
{"target": -1.4396631075885904, "params": {"model__colsample_bylevel": 1.0, "model__colsample_bynode": 0.3, "model__colsample_bytree": 1.0, "model__learning_rate": 0.3, "model__max_depth": 5.097578191241701, "model__n_estimators": 26.390481496206696, "model__reg_lambda": 0.0}, "datetime": {"datetime": "2021-03-27 01:13:46", "elapsed": 92.369143, "delta": 2.003841}}
{"target": -1.4725648404733427, "params": {"model__colsample_bylevel": 1.0, "model__colsample_bynode": 0.3, "model__colsample_bytree": 1.0, "model__learning_rate": 0.3, "model__max_depth": 3.6505112450900428, "model__n_estimators": 19.400175932545498, "model__reg_lambda": 10.0}, "datetime": {"datetime": "2021-03-27 01:13:48", "elapsed": 94.392221, "delta": 2.023078}}
{"target": -1.4692922157599875, "params": {"model__colsample_bylevel": 1.0, "model__colsample_bynode": 0.3, "model__colsample_bytree": 0.3, "model__learning_rate": 0.1, "model__max_depth": 6.72654220726004, "model__n_estimators": 30.0, "model__reg_lambda": 0.0}, "datetime": {"datetime": "2021-03-27 01:13:50", "elapsed": 96.281609, "delta": 1.889388}}
{"target": -1.4953824404735063, "params": {"model__colsample_bylevel": 0.3, "model__colsample_bynode": 1.0, "model__colsample_bytree": 1.0, "model__learning_rate": 0.3, "model__max_depth": 5.2960817605517585, "model__n_estimators": 15.0, "model__reg_lambda": 10.0}, "datetime": {"datetime": "2021-03-27 01:13:52", "elapsed": 98.375268, "delta": 2.093659}}
{"target": -1.5327356710598088, "params": {"model__colsample_bylevel": 0.3, "model__colsample_bynode": 0.3, "model__colsample_bytree": 0.3, "model__learning_rate": 0.3, "model__max_depth": 8.0, "model__n_estimators": 18.955107419392405, "model__reg_lambda": 1.1597371829345011}, "datetime": {"datetime": "2021-03-27 01:13:53", "elapsed": 99.854325, "delta": 1.479057}}
{"target": -1.4431350153425464, "params": {"model__colsample_bylevel": 0.3, "model__colsample_bynode": 1.0, "model__colsample_bytree": 0.3, "model__learning_rate": 0.3, "model__max_depth": 8.0, "model__n_estimators": 30.0, "model__reg_lambda": 7.529107586794284}, "datetime": {"datetime": "2021-03-27 01:13:55", "elapsed": 101.722866, "delta": 1.868541}}
{"target": -1.4488734141882995, "params": {"model__colsample_bylevel": 0.3, "model__colsample_bynode": 1.0, "model__colsample_bytree": 1.0, "model__learning_rate": 0.3, "model__max_depth": 3.7438545042889886, "model__n_estimators": 22.707986213533175, "model__reg_lambda": 7.624740749566839}, "datetime": {"datetime": "2021-03-27 01:13:57", "elapsed": 103.579365, "delta": 1.856499}}
{"target": -1.4589610004392655, "params": {"model__colsample_bylevel": 0.3, "model__colsample_bynode": 1.0, "model__colsample_bytree": 0.3, "model__learning_rate": 0.3, "model__max_depth": 3.8085207802929046, "model__n_estimators": 27.896404963499595, "model__reg_lambda": 10.0}, "datetime": {"datetime": "2021-03-27 01:13:59", "elapsed": 105.588025, "delta": 2.00866}}
{"target": -1.4496219141678748, "params": {"model__colsample_bylevel": 1.0, "model__colsample_bynode": 0.3, "model__colsample_bytree": 0.3, "model__learning_rate": 0.3, "model__max_depth": 3.7716802067698567, "model__n_estimators": 28.149078309981327, "model__reg_lambda": 5.873249734866999}, "datetime": {"datetime": "2021-03-27 01:14:01", "elapsed": 107.37539, "delta": 1.787365}}
{"target": -1.4441876628598116, "params": {"model__colsample_bylevel": 1.0, "model__colsample_bynode": 1.0, "model__colsample_bytree": 1.0, "model__learning_rate": 0.3, "model__max_depth": 3.954202305187129, "model__n_estimators": 30.0, "model__reg_lambda": 10.0}, "datetime": {"datetime": "2021-03-27 01:14:04", "elapsed": 110.508111, "delta": 3.132721}}
{"target": -1.3916783405629838, "params": {"model__colsample_bylevel": 1.0, "model__colsample_bynode": 0.3, "model__colsample_bytree": 1.0, "model__learning_rate": 0.3, "model__max_depth": 3.0155847863364236, "model__n_estimators": 20.716776261883886, "model__reg_lambda": 1.3950237025621883}, "datetime": {"datetime": "2021-03-27 01:14:06", "elapsed": 112.361349, "delta": 1.853238}}
{"target": -1.3902444774042007, "params": {"model__colsample_bylevel": 0.3, "model__colsample_bynode": 1.0, "model__colsample_bytree": 1.0, "model__learning_rate": 0.3, "model__max_depth": 8.0, "model__n_estimators": 23.536613627391095, "model__reg_lambda": 3.7706144351871624}, "datetime": {"datetime": "2021-03-27 01:14:08", "elapsed": 114.342549, "delta": 1.9812}}
{"target": -1.431158075283241, "params": {"model__colsample_bylevel": 0.3, "model__colsample_bynode": 0.3, "model__colsample_bytree": 1.0, "model__learning_rate": 0.3, "model__max_depth": 8.0, "model__n_estimators": 27.963909397629806, "model__reg_lambda": 10.0}, "datetime": {"datetime": "2021-03-27 01:14:10", "elapsed": 116.236083, "delta": 1.893534}}
{"target": -1.4648860416469582, "params": {"model__colsample_bylevel": 0.3, "model__colsample_bynode": 1.0, "model__colsample_bytree": 0.3, "model__learning_rate": 0.3, "model__max_depth": 8.0, "model__n_estimators": 23.68314599257609, "model__reg_lambda": 10.0}, "datetime": {"datetime": "2021-03-27 01:14:12", "elapsed": 118.053136, "delta": 1.817053}}
{"target": -1.4844520842116595, "params": {"model__colsample_bylevel": 1.0, "model__colsample_bynode": 1.0, "model__colsample_bytree": 1.0, "model__learning_rate": 0.3, "model__max_depth": 2.0, "model__n_estimators": 28.346944368861465, "model__reg_lambda": 8.755714562118397}, "datetime": {"datetime": "2021-03-27 01:14:14", "elapsed": 120.623354, "delta": 2.570218}}
{"target": -1.4690676796466005, "params": {"model__colsample_bylevel": 0.3, "model__colsample_bynode": 0.3, "model__colsample_bytree": 1.0, "model__learning_rate": 0.3, "model__max_depth": 4.27969967653696, "model__n_estimators": 15.0, "model__reg_lambda": 2.190708799033717}, "datetime": {"datetime": "2021-03-27 01:14:16", "elapsed": 122.422437, "delta": 1.799083}}
{"target": -1.4215714987475372, "params": {"model__colsample_bylevel": 1.0, "model__colsample_bynode": 0.3, "model__colsample_bytree": 1.0, "model__learning_rate": 0.3, "model__max_depth": 2.0, "model__n_estimators": 22.68320614760727, "model__reg_lambda": 0.0}, "datetime": {"datetime": "2021-03-27 01:14:18", "elapsed": 124.666057, "delta": 2.24362}}
{"target": -1.5024329554532534, "params": {"model__colsample_bylevel": 0.3, "model__colsample_bynode": 1.0, "model__colsample_bytree": 0.3, "model__learning_rate": 0.3, "model__max_depth": 4.244726980489013, "model__n_estimators": 20.895713554539206, "model__reg_lambda": 10.0}, "datetime": {"datetime": "2021-03-27 01:14:20", "elapsed": 126.545971, "delta": 1.879914}}
{"target": -1.4654172941952932, "params": {"model__colsample_bylevel": 0.3, "model__colsample_bynode": 0.3, "model__colsample_bytree": 1.0, "model__learning_rate": 0.3, "model__max_depth": 6.890297470300671, "model__n_estimators": 28.16912129786738, "model__reg_lambda": 0.0}, "datetime": {"datetime": "2021-03-27 01:14:22", "elapsed": 128.312963, "delta": 1.766992}}
{"target": -1.4275802207287347, "params": {"model__colsample_bylevel": 0.3, "model__colsample_bynode": 1.0, "model__colsample_bytree": 1.0, "model__learning_rate": 0.3, "model__max_depth": 3.9603322299223174, "model__n_estimators": 28.81216485984583, "model__reg_lambda": 6.5746426798234445}, "datetime": {"datetime": "2021-03-27 01:14:24", "elapsed": 130.76963, "delta": 2.456667}}
{"target": -1.4916061579479254, "params": {"model__colsample_bylevel": 1.0, "model__colsample_bynode": 0.3, "model__colsample_bytree": 1.0, "model__learning_rate": 0.1, "model__max_depth": 8.0, "model__n_estimators": 30.0, "model__reg_lambda": 1.7806225082057734}, "datetime": {"datetime": "2021-03-27 01:14:27", "elapsed": 133.461982, "delta": 2.692352}}
{"target": -1.5134874671805596, "params": {"model__colsample_bylevel": 1.0, "model__colsample_bynode": 0.3, "model__colsample_bytree": 1.0, "model__learning_rate": 0.3, "model__max_depth": 2.0, "model__n_estimators": 15.0, "model__reg_lambda": 5.799546525849377}, "datetime": {"datetime": "2021-03-27 01:14:29", "elapsed": 135.034023, "delta": 1.572041}}
{"target": -1.4176260995563879, "params": {"model__colsample_bylevel": 1.0, "model__colsample_bynode": 0.3, "model__colsample_bytree": 1.0, "model__learning_rate": 0.3, "model__max_depth": 8.0, "model__n_estimators": 24.18594100517924, "model__reg_lambda": 2.7390186277689996}, "datetime": {"datetime": "2021-03-27 01:14:31", "elapsed": 137.397082, "delta": 2.363059}}
{"target": -1.4248460836499335, "params": {"model__colsample_bylevel": 1.0, "model__colsample_bynode": 0.3, "model__colsample_bytree": 1.0, "model__learning_rate": 0.3, "model__max_depth": 5.060049595868667, "model__n_estimators": 17.298330585338046, "model__reg_lambda": 0.0}, "datetime": {"datetime": "2021-03-27 01:14:33", "elapsed": 139.410956, "delta": 2.013874}}
{"target": -1.4060542678096049, "params": {"model__colsample_bylevel": 0.3, "model__colsample_bynode": 0.3, "model__colsample_bytree": 1.0, "model__learning_rate": 0.3, "model__max_depth": 5.933256660968516, "model__n_estimators": 23.504758549120073, "model__reg_lambda": 1.4824287030677104}, "datetime": {"datetime": "2021-03-27 01:14:35", "elapsed": 141.337068, "delta": 1.926112}}
{"target": -1.5444405213025385, "params": {"model__colsample_bylevel": 1.0, "model__colsample_bynode": 1.0, "model__colsample_bytree": 1.0, "model__learning_rate": 0.1, "model__max_depth": 3.7656700620711026, "model__n_estimators": 30.0, "model__reg_lambda": 3.0623886001186484}, "datetime": {"datetime": "2021-03-27 01:14:38", "elapsed": 144.705673, "delta": 3.368605}}
{"target": -1.4924622611453136, "params": {"model__colsample_bylevel": 1.0, "model__colsample_bynode": 1.0, "model__colsample_bytree": 1.0, "model__learning_rate": 0.3, "model__max_depth": 5.3845234317774775, "model__n_estimators": 18.375653102630704, "model__reg_lambda": 10.0}, "datetime": {"datetime": "2021-03-27 01:14:41", "elapsed": 147.6568, "delta": 2.951127}}
{"target": -1.441863313657434, "params": {"model__colsample_bylevel": 1.0, "model__colsample_bynode": 1.0, "model__colsample_bytree": 1.0, "model__learning_rate": 0.3, "model__max_depth": 5.3015394425705065, "model__n_estimators": 19.729433660509763, "model__reg_lambda": 4.254692983507938}, "datetime": {"datetime": "2021-03-27 01:14:44", "elapsed": 150.310212, "delta": 2.653412}}
{"target": -1.4190734101621354, "params": {"model__colsample_bylevel": 0.3, "model__colsample_bynode": 1.0, "model__colsample_bytree": 1.0, "model__learning_rate": 0.3, "model__max_depth": 8.0, "model__n_estimators": 21.121251489524635, "model__reg_lambda": 4.962511862988756}, "datetime": {"datetime": "2021-03-27 01:14:46", "elapsed": 152.404773, "delta": 2.094561}}
{"target": -1.4913752083545146, "params": {"model__colsample_bylevel": 0.3, "model__colsample_bynode": 0.3, "model__colsample_bytree": 0.3, "model__learning_rate": 0.3, "model__max_depth": 6.359678242867664, "model__n_estimators": 29.132260970065655, "model__reg_lambda": 6.623686297605097}, "datetime": {"datetime": "2021-03-27 01:14:48", "elapsed": 154.195186, "delta": 1.790413}}
{"target": -1.4912294779269808, "params": {"model__colsample_bylevel": 1.0, "model__colsample_bynode": 1.0, "model__colsample_bytree": 0.3, "model__learning_rate": 0.3, "model__max_depth": 2.0, "model__n_estimators": 21.938759768704667, "model__reg_lambda": 8.10199708962794}, "datetime": {"datetime": "2021-03-27 01:14:50", "elapsed": 156.001777, "delta": 1.806591}}
{"target": -1.443178037877964, "params": {"model__colsample_bylevel": 1.0, "model__colsample_bynode": 0.3, "model__colsample_bytree": 1.0, "model__learning_rate": 0.3, "model__max_depth": 8.0, "model__n_estimators": 16.69380500128411, "model__reg_lambda": 3.5264251484636904}, "datetime": {"datetime": "2021-03-27 01:14:52", "elapsed": 158.317987, "delta": 2.31621}}
{"target": -1.462948592549757, "params": {"model__colsample_bylevel": 0.3, "model__colsample_bynode": 0.3, "model__colsample_bytree": 1.0, "model__learning_rate": 0.3, "model__max_depth": 8.0, "model__n_estimators": 22.205432519838133, "model__reg_lambda": 10.0}, "datetime": {"datetime": "2021-03-27 01:14:54", "elapsed": 160.33008, "delta": 2.012093}}
{"target": -1.4367986456680018, "params": {"model__colsample_bylevel": 1.0, "model__colsample_bynode": 1.0, "model__colsample_bytree": 0.3, "model__learning_rate": 0.3, "model__max_depth": 8.0, "model__n_estimators": 25.605091046561228, "model__reg_lambda": 6.040133552000559}, "datetime": {"datetime": "2021-03-27 01:14:57", "elapsed": 162.889178, "delta": 2.559098}}
{"target": -1.4714752893489988, "params": {"model__colsample_bylevel": 0.3, "model__colsample_bynode": 1.0, "model__colsample_bytree": 0.3, "model__learning_rate": 0.3, "model__max_depth": 4.018275399044321, "model__n_estimators": 16.69471311179382, "model__reg_lambda": 0.0}, "datetime": {"datetime": "2021-03-27 01:14:58", "elapsed": 164.644543, "delta": 1.755365}}
{"target": -1.4345658577978608, "params": {"model__colsample_bylevel": 0.3, "model__colsample_bynode": 0.6011297510744924, "model__colsample_bytree": 1.0, "model__learning_rate": 0.3, "model__max_depth": 8.0, "model__n_estimators": 25.676300788335713, "model__reg_lambda": 7.460059496824511}, "datetime": {"datetime": "2021-03-27 01:15:00", "elapsed": 166.570795, "delta": 1.926252}}
{"target": -1.4544774182896685, "params": {"model__colsample_bylevel": 1.0, "model__colsample_bynode": 1.0, "model__colsample_bytree": 1.0, "model__learning_rate": 0.3, "model__max_depth": 8.0, "model__n_estimators": 28.379780655732365, "model__reg_lambda": 10.0}, "datetime": {"datetime": "2021-03-27 01:15:04", "elapsed": 170.584274, "delta": 4.013479}}
{"target": -1.4168749742614835, "params": {"model__colsample_bylevel": 1.0, "model__colsample_bynode": 0.3, "model__colsample_bytree": 1.0, "model__learning_rate": 0.3, "model__max_depth": 3.1573325533837076, "model__n_estimators": 28.27758516957378, "model__reg_lambda": 10.0}, "datetime": {"datetime": "2021-03-27 01:15:06", "elapsed": 172.620131, "delta": 2.035857}}
{"target": -1.4519993529992476, "params": {"model__colsample_bylevel": 1.0, "model__colsample_bynode": 1.0, "model__colsample_bytree": 1.0, "model__learning_rate": 0.3, "model__max_depth": 8.0, "model__n_estimators": 29.138348221091974, "model__reg_lambda": 5.6652600190129165}, "datetime": {"datetime": "2021-03-27 01:15:10", "elapsed": 175.885432, "delta": 3.265301}}
{"target": -1.402495420578381, "params": {"model__colsample_bylevel": 0.3, "model__colsample_bynode": 1.0, "model__colsample_bytree": 1.0, "model__learning_rate": 0.3, "model__max_depth": 2.0, "model__n_estimators": 20.715902214794482, "model__reg_lambda": 1.9834837820177325}, "datetime": {"datetime": "2021-03-27 01:15:12", "elapsed": 178.100218, "delta": 2.214786}}
{"target": -1.5567626836345247, "params": {"model__colsample_bylevel": 0.3, "model__colsample_bynode": 0.3, "model__colsample_bytree": 0.3, "model__learning_rate": 0.3, "model__max_depth": 2.0, "model__n_estimators": 30.0, "model__reg_lambda": 2.5122709454953585}, "datetime": {"datetime": "2021-03-27 01:15:14", "elapsed": 179.975861, "delta": 1.875643}}
{"target": -1.4401747904032927, "params": {"model__colsample_bylevel": 1.0, "model__colsample_bynode": 0.3, "model__colsample_bytree": 1.0, "model__learning_rate": 0.3, "model__max_depth": 8.0, "model__n_estimators": 22.62040138620498, "model__reg_lambda": 0.0}, "datetime": {"datetime": "2021-03-27 01:15:16", "elapsed": 182.110824, "delta": 2.134963}}
{"target": -1.567780427850675, "params": {"model__colsample_bylevel": 0.3, "model__colsample_bynode": 0.3, "model__colsample_bytree": 0.3, "model__learning_rate": 0.3, "model__max_depth": 2.0, "model__n_estimators": 20.620292512266925, "model__reg_lambda": 1.0749526079618923}, "datetime": {"datetime": "2021-03-27 01:15:18", "elapsed": 184.239468, "delta": 2.128644}}
{"target": -1.4681437244098903, "params": {"model__colsample_bylevel": 1.0, "model__colsample_bynode": 1.0, "model__colsample_bytree": 1.0, "model__learning_rate": 0.3, "model__max_depth": 2.0, "model__n_estimators": 17.751930442274, "model__reg_lambda": 0.0}, "datetime": {"datetime": "2021-03-27 01:15:20", "elapsed": 186.576027, "delta": 2.336559}}
{"target": -1.3974856596521064, "params": {"model__colsample_bylevel": 1.0, "model__colsample_bynode": 0.3, "model__colsample_bytree": 1.0, "model__learning_rate": 0.3, "model__max_depth": 4.198683924800801, "model__n_estimators": 27.4237477426809, "model__reg_lambda": 4.029445111346712}, "datetime": {"datetime": "2021-03-27 01:15:22", "elapsed": 188.820821, "delta": 2.244794}}
{"target": -1.5755723365574088, "params": {"model__colsample_bylevel": 1.0, "model__colsample_bynode": 1.0, "model__colsample_bytree": 1.0, "model__learning_rate": 0.3, "model__max_depth": 4.338101603380081, "model__n_estimators": 19.748589437889176, "model__reg_lambda": 0.0}, "datetime": {"datetime": "2021-03-27 01:15:25", "elapsed": 191.441638, "delta": 2.620817}}
{"target": -1.3986042069129485, "params": {"model__colsample_bylevel": 1.0, "model__colsample_bynode": 0.41198693019864113, "model__colsample_bytree": 1.0, "model__learning_rate": 0.3, "model__max_depth": 2.0, "model__n_estimators": 28.797577031949178, "model__reg_lambda": 0.0}, "datetime": {"datetime": "2021-03-27 01:15:27", "elapsed": 193.558359, "delta": 2.116721}}
{"target": -1.4959299704869804, "params": {"model__colsample_bylevel": 1.0, "model__colsample_bynode": 1.0, "model__colsample_bytree": 1.0, "model__learning_rate": 0.3, "model__max_depth": 2.0, "model__n_estimators": 19.95727161365312, "model__reg_lambda": 5.409591819181896}, "datetime": {"datetime": "2021-03-27 01:15:30", "elapsed": 196.31075, "delta": 2.752391}}
{"target": -1.4284560152208026, "params": {"model__colsample_bylevel": 0.3, "model__colsample_bynode": 1.0, "model__colsample_bytree": 1.0, "model__learning_rate": 0.3, "model__max_depth": 3.5648048887137396, "model__n_estimators": 22.041802520763028, "model__reg_lambda": 2.3031182201940443}, "datetime": {"datetime": "2021-03-27 01:15:32", "elapsed": 198.473463, "delta": 2.162713}}
{"target": -1.4459297139224583, "params": {"model__colsample_bylevel": 0.3, "model__colsample_bynode": 0.3, "model__colsample_bytree": 1.0, "model__learning_rate": 0.3, "model__max_depth": 3.776026421441973, "model__n_estimators": 16.651718815111234, "model__reg_lambda": 0.0}, "datetime": {"datetime": "2021-03-27 01:15:34", "elapsed": 200.701199, "delta": 2.227736}}
{"target": -1.4853493473641033, "params": {"model__colsample_bylevel": 1.0, "model__colsample_bynode": 0.3, "model__colsample_bytree": 0.3, "model__learning_rate": 0.3, "model__max_depth": 8.0, "model__n_estimators": 28.00425164401813, "model__reg_lambda": 0.0}, "datetime": {"datetime": "2021-03-27 01:15:36", "elapsed": 202.32043, "delta": 1.619231}}
{"target": -1.5302622525804284, "params": {"model__colsample_bylevel": 0.3, "model__colsample_bynode": 0.3, "model__colsample_bytree": 1.0, "model__learning_rate": 0.3, "model__max_depth": 8.0, "model__n_estimators": 15.0, "model__reg_lambda": 10.0}, "datetime": {"datetime": "2021-03-27 01:15:38", "elapsed": 204.014656, "delta": 1.694226}}
{"target": -1.4441353801786359, "params": {"model__colsample_bylevel": 0.3, "model__colsample_bynode": 0.3, "model__colsample_bytree": 1.0, "model__learning_rate": 0.3, "model__max_depth": 7.332174649127141, "model__n_estimators": 24.728744152413622, "model__reg_lambda": 4.721434811577674}, "datetime": {"datetime": "2021-03-27 01:15:39", "elapsed": 205.6743, "delta": 1.659644}}
{"target": -1.4134948886080605, "params": {"model__colsample_bylevel": 1.0, "model__colsample_bynode": 0.3, "model__colsample_bytree": 1.0, "model__learning_rate": 0.3, "model__max_depth": 3.330935945437567, "model__n_estimators": 30.0, "model__reg_lambda": 7.767639525291295}, "datetime": {"datetime": "2021-03-27 01:15:41", "elapsed": 207.761573, "delta": 2.087273}}
{"target": -1.434156047216738, "params": {"model__colsample_bylevel": 0.3, "model__colsample_bynode": 1.0, "model__colsample_bytree": 1.0, "model__learning_rate": 0.3, "model__max_depth": 4.219290535917136, "model__n_estimators": 26.08743226402245, "model__reg_lambda": 6.821949959627377}, "datetime": {"datetime": "2021-03-27 01:15:44", "elapsed": 209.922339, "delta": 2.160766}}
{"target": -1.4581577983644347, "params": {"model__colsample_bylevel": 1.0, "model__colsample_bynode": 1.0, "model__colsample_bytree": 1.0, "model__learning_rate": 0.3, "model__max_depth": 2.0, "model__n_estimators": 22.37406479390265, "model__reg_lambda": 1.5226231177630205}, "datetime": {"datetime": "2021-03-27 01:15:46", "elapsed": 212.093108, "delta": 2.170769}}
{"target": -1.4709646092106898, "params": {"model__colsample_bylevel": 1.0, "model__colsample_bynode": 0.3, "model__colsample_bytree": 1.0, "model__learning_rate": 0.3, "model__max_depth": 5.052288089336109, "model__n_estimators": 15.0, "model__reg_lambda": 5.43040443401848}, "datetime": {"datetime": "2021-03-27 01:15:48", "elapsed": 214.171846, "delta": 2.078738}}
{"target": -1.394216919309743, "params": {"model__colsample_bylevel": 1.0, "model__colsample_bynode": 0.3, "model__colsample_bytree": 0.3, "model__learning_rate": 0.3, "model__max_depth": 2.0, "model__n_estimators": 25.23995991954956, "model__reg_lambda": 0.0}, "datetime": {"datetime": "2021-03-27 01:15:50", "elapsed": 215.968079, "delta": 1.796233}}
{"target": -1.4291274032407049, "params": {"model__colsample_bylevel": 0.3095683179282123, "model__colsample_bynode": 0.8407973711346317, "model__colsample_bytree": 0.30277768814467165, "model__learning_rate": 0.18734746494254234, "model__max_depth": 2.0347533271889873, "model__n_estimators": 24.14536175875451, "model__reg_lambda": 0.1993317406175832}, "datetime": {"datetime": "2021-03-27 01:15:52", "elapsed": 218.046215, "delta": 2.078136}}
{"target": -1.4625051284775785, "params": {"model__colsample_bylevel": 0.3, "model__colsample_bynode": 0.3, "model__colsample_bytree": 1.0, "model__learning_rate": 0.3, "model__max_depth": 2.0, "model__n_estimators": 30.0, "model__reg_lambda": 10.0}, "datetime": {"datetime": "2021-03-27 01:15:53", "elapsed": 219.721707, "delta": 1.675492}}
{"target": -1.4253624464115262, "params": {"model__colsample_bylevel": 1.0, "model__colsample_bynode": 0.3, "model__colsample_bytree": 1.0, "model__learning_rate": 0.3, "model__max_depth": 6.421560821775105, "model__n_estimators": 20.601745104341145, "model__reg_lambda": 1.8226285867257432}, "datetime": {"datetime": "2021-03-27 01:15:55", "elapsed": 221.618001, "delta": 1.896294}}
{"target": -1.4662493636642677, "params": {"model__colsample_bylevel": 1.0, "model__colsample_bynode": 1.0, "model__colsample_bytree": 1.0, "model__learning_rate": 0.3, "model__max_depth": 4.58578056030452, "model__n_estimators": 20.32807789092589, "model__reg_lambda": 9.14488678084427}, "datetime": {"datetime": "2021-03-27 01:15:58", "elapsed": 224.835335, "delta": 3.217334}}
{"target": -1.5553335945351399, "params": {"model__colsample_bylevel": 1.0, "model__colsample_bynode": 0.3, "model__colsample_bytree": 0.3, "model__learning_rate": 0.3, "model__max_depth": 5.349256370230276, "model__n_estimators": 15.0, "model__reg_lambda": 10.0}, "datetime": {"datetime": "2021-03-27 01:16:00", "elapsed": 226.725501, "delta": 1.890166}}
{"target": -1.4755646200823613, "params": {"model__colsample_bylevel": 0.7240205311766443, "model__colsample_bynode": 0.8301409402109441, "model__colsample_bytree": 0.847351585527544, "model__learning_rate": 0.2896806729181496, "model__max_depth": 2.0148821923820073, "model__n_estimators": 23.854082773046187, "model__reg_lambda": 9.953440319781631}, "datetime": {"datetime": "2021-03-27 01:16:03", "elapsed": 228.925504, "delta": 2.200003}}
{"target": -1.4646229698228233, "params": {"model__colsample_bylevel": 1.0, "model__colsample_bynode": 0.3, "model__colsample_bytree": 0.3, "model__learning_rate": 0.3, "model__max_depth": 8.0, "model__n_estimators": 25.232021992576122, "model__reg_lambda": 10.0}, "datetime": {"datetime": "2021-03-27 01:16:04", "elapsed": 230.792629, "delta": 1.867125}}
{"target": -1.4240212338693117, "params": {"model__colsample_bylevel": 1.0, "model__colsample_bynode": 0.3, "model__colsample_bytree": 1.0, "model__learning_rate": 0.3, "model__max_depth": 5.124183032261591, "model__n_estimators": 28.472889093732103, "model__reg_lambda": 8.938192761704085}, "datetime": {"datetime": "2021-03-27 01:16:07", "elapsed": 233.14529, "delta": 2.352661}}
{"target": -1.5078913248589507, "params": {"model__colsample_bylevel": 1.0, "model__colsample_bynode": 0.3, "model__colsample_bytree": 0.3, "model__learning_rate": 0.3, "model__max_depth": 2.0, "model__n_estimators": 21.99936262583099, "model__reg_lambda": 10.0}, "datetime": {"datetime": "2021-03-27 01:16:09", "elapsed": 234.899932, "delta": 1.754642}}
{"target": -1.4705842983274573, "params": {"model__colsample_bylevel": 0.3, "model__colsample_bynode": 0.3, "model__colsample_bytree": 0.3, "model__learning_rate": 0.3, "model__max_depth": 4.5172521868694515, "model__n_estimators": 24.109994671531037, "model__reg_lambda": 0.0}, "datetime": {"datetime": "2021-03-27 01:16:11", "elapsed": 237.046982, "delta": 2.14705}}
{"target": -1.4398540900291308, "params": {"model__colsample_bylevel": 1.0, "model__colsample_bynode": 1.0, "model__colsample_bytree": 0.3, "model__learning_rate": 0.3, "model__max_depth": 2.0, "model__n_estimators": 26.790127036548387, "model__reg_lambda": 0.0}, "datetime": {"datetime": "2021-03-27 01:16:13", "elapsed": 238.89771, "delta": 1.850728}}
{"target": -1.4256617672147525, "params": {"model__colsample_bylevel": 0.3, "model__colsample_bynode": 1.0, "model__colsample_bytree": 1.0, "model__learning_rate": 0.3, "model__max_depth": 8.0, "model__n_estimators": 16.67898170125967, "model__reg_lambda": 3.7837739143556157}, "datetime": {"datetime": "2021-03-27 01:16:15", "elapsed": 240.888147, "delta": 1.990437}}
{"target": -1.424357339595377, "params": {"model__colsample_bylevel": 0.3, "model__colsample_bynode": 0.3, "model__colsample_bytree": 1.0, "model__learning_rate": 0.3, "model__max_depth": 4.170684977845383, "model__n_estimators": 25.693267174055716, "model__reg_lambda": 1.5945590178282099}, "datetime": {"datetime": "2021-03-27 01:16:16", "elapsed": 242.80705, "delta": 1.918903}}
{"target": -1.4667252674779814, "params": {"model__colsample_bylevel": 1.0, "model__colsample_bynode": 1.0, "model__colsample_bytree": 1.0, "model__learning_rate": 0.3, "model__max_depth": 3.4171761348469056, "model__n_estimators": 16.73672328363256, "model__reg_lambda": 3.8275772080414394}, "datetime": {"datetime": "2021-03-27 01:16:19", "elapsed": 245.393347, "delta": 2.586297}}
{"target": -1.4456971919717456, "params": {"model__colsample_bylevel": 0.3, "model__colsample_bynode": 1.0, "model__colsample_bytree": 1.0, "model__learning_rate": 0.3, "model__max_depth": 4.062522057685754, "model__n_estimators": 18.722935434394874, "model__reg_lambda": 6.116029166983612}, "datetime": {"datetime": "2021-03-27 01:16:21", "elapsed": 247.286623, "delta": 1.893276}}
{"target": -1.443932734694386, "params": {"model__colsample_bylevel": 1.0, "model__colsample_bynode": 1.0, "model__colsample_bytree": 0.3, "model__learning_rate": 0.3, "model__max_depth": 4.460055269765495, "model__n_estimators": 21.991323856595937, "model__reg_lambda": 6.3174417024608145}, "datetime": {"datetime": "2021-03-27 01:16:23", "elapsed": 249.345004, "delta": 2.058381}}
{"target": -1.4357058949512091, "params": {"model__colsample_bylevel": 1.0, "model__colsample_bynode": 0.3, "model__colsample_bytree": 0.3, "model__learning_rate": 0.3, "model__max_depth": 6.1826889604098865, "model__n_estimators": 30.0, "model__reg_lambda": 3.391005532618617}, "datetime": {"datetime": "2021-03-27 01:16:25", "elapsed": 251.454564, "delta": 2.10956}}
{"target": -1.4772797692455755, "params": {"model__colsample_bylevel": 0.3, "model__colsample_bynode": 0.3, "model__colsample_bytree": 1.0, "model__learning_rate": 0.3, "model__max_depth": 6.440076981649088, "model__n_estimators": 16.99847145823729, "model__reg_lambda": 0.0}, "datetime": {"datetime": "2021-03-27 01:16:27", "elapsed": 253.430725, "delta": 1.976161}}
{"target": -1.501383853631526, "params": {"model__colsample_bylevel": 1.0, "model__colsample_bynode": 0.3, "model__colsample_bytree": 0.3, "model__learning_rate": 0.3, "model__max_depth": 4.882166203152916, "model__n_estimators": 15.880585052911822, "model__reg_lambda": 0.0}, "datetime": {"datetime": "2021-03-27 01:16:29", "elapsed": 255.466131, "delta": 2.035406}}
{"target": -1.455729613053626, "params": {"model__colsample_bylevel": 1.0, "model__colsample_bynode": 0.3, "model__colsample_bytree": 0.3, "model__learning_rate": 0.3, "model__max_depth": 5.43082153189431, "model__n_estimators": 28.601779692556516, "model__reg_lambda": 0.8198159034695832}, "datetime": {"datetime": "2021-03-27 01:16:31", "elapsed": 257.218862, "delta": 1.752731}}
{"target": -1.453249638684202, "params": {"model__colsample_bylevel": 0.3, "model__colsample_bynode": 1.0, "model__colsample_bytree": 0.3, "model__learning_rate": 0.3, "model__max_depth": 8.0, "model__n_estimators": 26.920123749173126, "model__reg_lambda": 10.0}, "datetime": {"datetime": "2021-03-27 01:16:33", "elapsed": 259.090633, "delta": 1.871771}}
{"target": -1.5272613466649816, "params": {"model__colsample_bylevel": 0.3, "model__colsample_bynode": 1.0, "model__colsample_bytree": 0.3, "model__learning_rate": 0.3, "model__max_depth": 3.272873536228579, "model__n_estimators": 15.0, "model__reg_lambda": 6.82343309803189}, "datetime": {"datetime": "2021-03-27 01:16:34", "elapsed": 260.80592, "delta": 1.715287}}
{"target": -1.451835693308301, "params": {"model__colsample_bylevel": 0.3, "model__colsample_bynode": 1.0, "model__colsample_bytree": 1.0, "model__learning_rate": 0.3, "model__max_depth": 2.0, "model__n_estimators": 22.1915829379869, "model__reg_lambda": 6.1086010112800135}, "datetime": {"datetime": "2021-03-27 01:16:36", "elapsed": 262.582582, "delta": 1.776662}}
{"target": -1.436501930008872, "params": {"model__colsample_bylevel": 1.0, "model__colsample_bynode": 1.0, "model__colsample_bytree": 0.3, "model__learning_rate": 0.3, "model__max_depth": 8.0, "model__n_estimators": 20.751925463318912, "model__reg_lambda": 3.0486108558417024}, "datetime": {"datetime": "2021-03-27 01:16:38", "elapsed": 264.510363, "delta": 1.927781}}
{"target": -1.4826955969148465, "params": {"model__colsample_bylevel": 1.0, "model__colsample_bynode": 0.3, "model__colsample_bytree": 0.3, "model__learning_rate": 0.3, "model__max_depth": 4.591618124200039, "model__n_estimators": 22.319605582337914, "model__reg_lambda": 1.5549446536610532}, "datetime": {"datetime": "2021-03-27 01:16:40", "elapsed": 266.70294, "delta": 2.192577}}
{"target": -1.5176742324146673, "params": {"model__colsample_bylevel": 0.3, "model__colsample_bynode": 0.3, "model__colsample_bytree": 1.0, "model__learning_rate": 0.1, "model__max_depth": 8.0, "model__n_estimators": 21.376260863567946, "model__reg_lambda": 0.0}, "datetime": {"datetime": "2021-03-27 01:16:42", "elapsed": 268.725485, "delta": 2.022545}}
{"target": -1.5821530550502347, "params": {"model__colsample_bylevel": 1.0, "model__colsample_bynode": 0.3, "model__colsample_bytree": 1.0, "model__learning_rate": 0.1, "model__max_depth": 2.0, "model__n_estimators": 20.26712423286378, "model__reg_lambda": 0.0}, "datetime": {"datetime": "2021-03-27 01:16:44", "elapsed": 270.533855, "delta": 1.80837}}
{"target": -1.382711019164518, "params": {"model__colsample_bylevel": 0.3, "model__colsample_bynode": 0.3, "model__colsample_bytree": 1.0, "model__learning_rate": 0.3, "model__max_depth": 2.1542432790436186, "model__n_estimators": 23.795681101415376, "model__reg_lambda": 0.0}, "datetime": {"datetime": "2021-03-27 01:16:46", "elapsed": 272.150272, "delta": 1.616417}}
{"target": -1.4501772862076219, "params": {"model__colsample_bylevel": 0.3, "model__colsample_bynode": 0.3, "model__colsample_bytree": 1.0, "model__learning_rate": 0.3, "model__max_depth": 4.342125390977777, "model__n_estimators": 20.444783175203263, "model__reg_lambda": 1.9737108447725795}, "datetime": {"datetime": "2021-03-27 01:16:48", "elapsed": 273.896845, "delta": 1.746573}}
{"target": -1.3943104078994888, "params": {"model__colsample_bylevel": 1.0, "model__colsample_bynode": 0.3, "model__colsample_bytree": 1.0, "model__learning_rate": 0.3, "model__max_depth": 2.548947338011263, "model__n_estimators": 30.0, "model__reg_lambda": 0.4507374105158454}, "datetime": {"datetime": "2021-03-27 01:16:50", "elapsed": 276.258612, "delta": 2.361767}}
{"target": -1.4204015647587567, "params": {"model__colsample_bylevel": 1.0, "model__colsample_bynode": 0.3, "model__colsample_bytree": 1.0, "model__learning_rate": 0.3, "model__max_depth": 2.782081289332336, "model__n_estimators": 18.181736784333314, "model__reg_lambda": 1.818584442888829}, "datetime": {"datetime": "2021-03-27 01:16:52", "elapsed": 278.609459, "delta": 2.350847}}
{"target": -1.4525796395186605, "params": {"model__colsample_bylevel": 0.3, "model__colsample_bynode": 0.3, "model__colsample_bytree": 1.0, "model__learning_rate": 0.3, "model__max_depth": 8.0, "model__n_estimators": 22.479497618341316, "model__reg_lambda": 2.482096810274493}, "datetime": {"datetime": "2021-03-27 01:16:54", "elapsed": 280.317529, "delta": 1.70807}}
{"target": -1.4125103584214018, "params": {"model__colsample_bylevel": 1.0, "model__colsample_bynode": 1.0, "model__colsample_bytree": 0.3, "model__learning_rate": 0.3, "model__max_depth": 8.0, "model__n_estimators": 20.013472358981833, "model__reg_lambda": 0.0}, "datetime": {"datetime": "2021-03-27 01:16:56", "elapsed": 282.619377, "delta": 2.301848}}
{"target": -1.5033568595009654, "params": {"model__colsample_bylevel": 0.3, "model__colsample_bynode": 1.0, "model__colsample_bytree": 0.3, "model__learning_rate": 0.3, "model__max_depth": 8.0, "model__n_estimators": 15.0, "model__reg_lambda": 0.0}, "datetime": {"datetime": "2021-03-27 01:16:58", "elapsed": 284.212824, "delta": 1.593447}}
{"target": -1.44724889886633, "params": {"model__colsample_bylevel": 1.0, "model__colsample_bynode": 0.3, "model__colsample_bytree": 1.0, "model__learning_rate": 0.3, "model__max_depth": 3.7882478623387277, "model__n_estimators": 23.538974428401588, "model__reg_lambda": 6.347055254589131}, "datetime": {"datetime": "2021-03-27 01:17:00", "elapsed": 286.419469, "delta": 2.206645}}
{"target": -1.434016455973134, "params": {"model__colsample_bylevel": 0.3, "model__colsample_bynode": 1.0, "model__colsample_bytree": 1.0, "model__learning_rate": 0.3, "model__max_depth": 6.462255010192869, "model__n_estimators": 23.335615580063994, "model__reg_lambda": 3.403412301222886}, "datetime": {"datetime": "2021-03-27 01:17:02", "elapsed": 288.512372, "delta": 2.092903}}
{"target": -1.4643769984120045, "params": {"model__colsample_bylevel": 1.0, "model__colsample_bynode": 0.3, "model__colsample_bytree": 1.0, "model__learning_rate": 0.3, "model__max_depth": 6.076934307967647, "model__n_estimators": 19.9273967842171, "model__reg_lambda": 10.0}, "datetime": {"datetime": "2021-03-27 01:17:04", "elapsed": 290.758121, "delta": 2.245749}}
{"target": -1.437645077753974, "params": {"model__colsample_bylevel": 0.3, "model__colsample_bynode": 1.0, "model__colsample_bytree": 1.0, "model__learning_rate": 0.3, "model__max_depth": 8.0, "model__n_estimators": 22.116903047687497, "model__reg_lambda": 8.284656225822655}, "datetime": {"datetime": "2021-03-27 01:17:07", "elapsed": 293.215577, "delta": 2.457456}}
{"target": -1.4537240171008678, "params": {"model__colsample_bylevel": 0.3, "model__colsample_bynode": 0.3, "model__colsample_bytree": 0.3, "model__learning_rate": 0.3, "model__max_depth": 7.230972515308189, "model__n_estimators": 30.0, "model__reg_lambda": 0.9606265472685934}, "datetime": {"datetime": "2021-03-27 01:17:09", "elapsed": 295.326949, "delta": 2.111372}}
{"target": -1.437063411727507, "params": {"model__colsample_bylevel": 1.0, "model__colsample_bynode": 0.3, "model__colsample_bytree": 1.0, "model__learning_rate": 0.3, "model__max_depth": 6.4715748850670805, "model__n_estimators": 24.460533573442344, "model__reg_lambda": 0.0}, "datetime": {"datetime": "2021-03-27 01:17:11", "elapsed": 297.563164, "delta": 2.236215}}
{"target": -1.4782944973369223, "params": {"model__colsample_bylevel": 1.0, "model__colsample_bynode": 1.0, "model__colsample_bytree": 1.0, "model__learning_rate": 0.3, "model__max_depth": 8.0, "model__n_estimators": 19.553384323434106, "model__reg_lambda": 2.882708499144172}, "datetime": {"datetime": "2021-03-27 01:17:14", "elapsed": 300.607255, "delta": 3.044091}}
{"target": -1.4431261479206707, "params": {"model__colsample_bylevel": 0.3, "model__colsample_bynode": 1.0, "model__colsample_bytree": 1.0, "model__learning_rate": 0.3, "model__max_depth": 8.0, "model__n_estimators": 23.544210822377753, "model__reg_lambda": 0.0}, "datetime": {"datetime": "2021-03-27 01:17:16", "elapsed": 302.813435, "delta": 2.20618}}
{"target": -1.4749944388974403, "params": {"model__colsample_bylevel": 1.0, "model__colsample_bynode": 0.3, "model__colsample_bytree": 0.3, "model__learning_rate": 0.3, "model__max_depth": 8.0, "model__n_estimators": 21.999854309258115, "model__reg_lambda": 8.350184568712411}, "datetime": {"datetime": "2021-03-27 01:17:19", "elapsed": 305.037858, "delta": 2.224423}}
{"target": -1.4882029836349513, "params": {"model__colsample_bylevel": 0.3, "model__colsample_bynode": 1.0, "model__colsample_bytree": 1.0, "model__learning_rate": 0.3, "model__max_depth": 6.457206454735686, "model__n_estimators": 15.0, "model__reg_lambda": 7.704068962912353}, "datetime": {"datetime": "2021-03-27 01:17:21", "elapsed": 307.085003, "delta": 2.047145}}
{"target": -1.519696483626098, "params": {"model__colsample_bylevel": 0.3, "model__colsample_bynode": 0.3, "model__colsample_bytree": 1.0, "model__learning_rate": 0.3, "model__max_depth": 2.0, "model__n_estimators": 15.0, "model__reg_lambda": 3.8119372151236073}, "datetime": {"datetime": "2021-03-27 01:17:23", "elapsed": 308.908768, "delta": 1.823765}}
{"target": -1.48022747868807, "params": {"model__colsample_bylevel": 1.0, "model__colsample_bynode": 1.0, "model__colsample_bytree": 1.0, "model__learning_rate": 0.3, "model__max_depth": 3.0931764733401033, "model__n_estimators": 20.109162923642394, "model__reg_lambda": 2.83133387472668}, "datetime": {"datetime": "2021-03-27 01:17:25", "elapsed": 311.596237, "delta": 2.687469}}
{"target": -1.40365064850455, "params": {"model__colsample_bylevel": 0.3, "model__colsample_bynode": 1.0, "model__colsample_bytree": 1.0, "model__learning_rate": 0.3, "model__max_depth": 2.3311396470355334, "model__n_estimators": 18.50675509903279, "model__reg_lambda": 0.7829415834597693}, "datetime": {"datetime": "2021-03-27 01:17:27", "elapsed": 313.282256, "delta": 1.686019}}
{"target": -1.4239432060335209, "params": {"model__colsample_bylevel": 1.0, "model__colsample_bynode": 0.3, "model__colsample_bytree": 1.0, "model__learning_rate": 0.3, "model__max_depth": 6.382205669673334, "model__n_estimators": 21.2551371567378, "model__reg_lambda": 5.871840877619782}, "datetime": {"datetime": "2021-03-27 01:17:29", "elapsed": 315.65601, "delta": 2.373754}}
{"target": -1.5145590062887557, "params": {"model__colsample_bylevel": 0.3, "model__colsample_bynode": 1.0, "model__colsample_bytree": 0.3, "model__learning_rate": 0.1, "model__max_depth": 7.49482568243821, "model__n_estimators": 28.8160609614135, "model__reg_lambda": 0.4064173311047889}, "datetime": {"datetime": "2021-03-27 01:17:32", "elapsed": 318.0875, "delta": 2.43149}}
{"target": -1.459331836531519, "params": {"model__colsample_bylevel": 1.0, "model__colsample_bynode": 0.3, "model__colsample_bytree": 1.0, "model__learning_rate": 0.3, "model__max_depth": 6.831456915722517, "model__n_estimators": 29.058206928103555, "model__reg_lambda": 1.1231275050467053}, "datetime": {"datetime": "2021-03-27 01:17:34", "elapsed": 320.369665, "delta": 2.282165}}
{"target": -1.4058314221047297, "params": {"model__colsample_bylevel": 0.40045844990019897, "model__colsample_bynode": 0.9853351434938893, "model__colsample_bytree": 0.5805258475147645, "model__learning_rate": 0.2629992953352098, "model__max_depth": 7.167487578127277, "model__n_estimators": 29.97034945639112, "model__reg_lambda": 3.917848580975034}, "datetime": {"datetime": "2021-03-27 01:17:37", "elapsed": 322.980204, "delta": 2.610539}}
{"target": -1.5430492675930692, "params": {"model__colsample_bylevel": 1.0, "model__colsample_bynode": 1.0, "model__colsample_bytree": 0.3, "model__learning_rate": 0.1, "model__max_depth": 6.319158452367752, "model__n_estimators": 30.0, "model__reg_lambda": 5.026203842006241}, "datetime": {"datetime": "2021-03-27 01:17:39", "elapsed": 325.53309, "delta": 2.552886}}
{"target": -1.449273627910061, "params": {"model__colsample_bylevel": 1.0, "model__colsample_bynode": 1.0, "model__colsample_bytree": 0.3, "model__learning_rate": 0.3, "model__max_depth": 3.8813894088889396, "model__n_estimators": 24.708805717338215, "model__reg_lambda": 10.0}, "datetime": {"datetime": "2021-03-27 01:17:41", "elapsed": 327.84531, "delta": 2.31222}}
{"target": -1.4513320067748967, "params": {"model__colsample_bylevel": 0.3, "model__colsample_bynode": 0.3, "model__colsample_bytree": 1.0, "model__learning_rate": 0.3, "model__max_depth": 4.106381940209467, "model__n_estimators": 24.155243474760002, "model__reg_lambda": 3.9832276886264584}, "datetime": {"datetime": "2021-03-27 01:17:44", "elapsed": 329.955278, "delta": 2.109968}}
{"target": -1.4170782270065199, "params": {"model__colsample_bylevel": 0.3, "model__colsample_bynode": 0.3, "model__colsample_bytree": 1.0, "model__learning_rate": 0.3, "model__max_depth": 8.0, "model__n_estimators": 30.0, "model__reg_lambda": 5.241889012649145}, "datetime": {"datetime": "2021-03-27 01:17:46", "elapsed": 332.432679, "delta": 2.477401}}
{"target": -1.4205587784746203, "params": {"model__colsample_bylevel": 1.0, "model__colsample_bynode": 0.3, "model__colsample_bytree": 1.0, "model__learning_rate": 0.3, "model__max_depth": 6.3476165214225375, "model__n_estimators": 25.356131797876582, "model__reg_lambda": 6.593908166504342}, "datetime": {"datetime": "2021-03-27 01:17:48", "elapsed": 334.575395, "delta": 2.142716}}
{"target": -1.4537446322364975, "params": {"model__colsample_bylevel": 1.0, "model__colsample_bynode": 0.3, "model__colsample_bytree": 0.3, "model__learning_rate": 0.3, "model__max_depth": 8.0, "model__n_estimators": 22.932132220256154, "model__reg_lambda": 4.712914328163365}, "datetime": {"datetime": "2021-03-27 01:17:51", "elapsed": 337.028322, "delta": 2.452927}}
{"target": -1.4346151682021826, "params": {"model__colsample_bylevel": 1.0, "model__colsample_bynode": 1.0, "model__colsample_bytree": 1.0, "model__learning_rate": 0.3, "model__max_depth": 4.070860253582596, "model__n_estimators": 28.38365233411711, "model__reg_lambda": 8.164799457016828}, "datetime": {"datetime": "2021-03-27 01:17:54", "elapsed": 340.365702, "delta": 3.33738}}
{"target": -1.4006987206745838, "params": {"model__colsample_bylevel": 0.3, "model__colsample_bynode": 1.0, "model__colsample_bytree": 1.0, "model__learning_rate": 0.3, "model__max_depth": 8.0, "model__n_estimators": 26.5427957272749, "model__reg_lambda": 4.1725292294484095}, "datetime": {"datetime": "2021-03-27 01:17:56", "elapsed": 342.439215, "delta": 2.073513}}
{"target": -1.4153948294322773, "params": {"model__colsample_bylevel": 0.3, "model__colsample_bynode": 0.4432711671780414, "model__colsample_bytree": 1.0, "model__learning_rate": 0.3, "model__max_depth": 5.40035753696873, "model__n_estimators": 27.666720189300477, "model__reg_lambda": 5.171918200508768}, "datetime": {"datetime": "2021-03-27 01:17:58", "elapsed": 344.479012, "delta": 2.039797}}
{"target": -1.4135384742804953, "params": {"model__colsample_bylevel": 0.3, "model__colsample_bynode": 1.0, "model__colsample_bytree": 1.0, "model__learning_rate": 0.3, "model__max_depth": 5.030735215988566, "model__n_estimators": 30.0, "model__reg_lambda": 8.15012081884849}, "datetime": {"datetime": "2021-03-27 01:18:01", "elapsed": 347.339181, "delta": 2.860169}}
{"target": -1.538234542493803, "params": {"model__colsample_bylevel": 0.3, "model__colsample_bynode": 0.3, "model__colsample_bytree": 1.0, "model__learning_rate": 0.3, "model__max_depth": 2.0, "model__n_estimators": 19.54115739799305, "model__reg_lambda": 7.604708660520239}, "datetime": {"datetime": "2021-03-27 01:18:03", "elapsed": 349.473902, "delta": 2.134721}}
{"target": -1.5291022056524737, "params": {"model__colsample_bylevel": 1.0, "model__colsample_bynode": 0.3, "model__colsample_bytree": 1.0, "model__learning_rate": 0.1, "model__max_depth": 2.0, "model__n_estimators": 26.458250086262375, "model__reg_lambda": 0.0}, "datetime": {"datetime": "2021-03-27 01:18:05", "elapsed": 351.449606, "delta": 1.975704}}
{"target": -1.4657127530300529, "params": {"model__colsample_bylevel": 0.3, "model__colsample_bynode": 1.0, "model__colsample_bytree": 0.3, "model__learning_rate": 0.3, "model__max_depth": 6.094142845074086, "model__n_estimators": 26.166032818080204, "model__reg_lambda": 6.502070035460572}, "datetime": {"datetime": "2021-03-27 01:18:08", "elapsed": 353.917127, "delta": 2.467521}}
{"target": -1.4855052389238246, "params": {"model__colsample_bylevel": 0.3, "model__colsample_bynode": 1.0, "model__colsample_bytree": 0.3, "model__learning_rate": 0.3, "model__max_depth": 6.370935739664147, "model__n_estimators": 19.171417035318598, "model__reg_lambda": 0.7834171143106231}, "datetime": {"datetime": "2021-03-27 01:18:10", "elapsed": 356.103432, "delta": 2.186305}}
{"target": -1.4252135218674504, "params": {"model__colsample_bylevel": 0.3, "model__colsample_bynode": 1.0, "model__colsample_bytree": 1.0, "model__learning_rate": 0.3, "model__max_depth": 3.2021229259326804, "model__n_estimators": 30.0, "model__reg_lambda": 8.866902357017887}, "datetime": {"datetime": "2021-03-27 01:18:12", "elapsed": 358.339693, "delta": 2.236261}}
{"target": -1.412373232540499, "params": {"model__colsample_bylevel": 1.0, "model__colsample_bynode": 0.3, "model__colsample_bytree": 1.0, "model__learning_rate": 0.3, "model__max_depth": 4.9080201870739435, "model__n_estimators": 29.637738687909977, "model__reg_lambda": 7.145738774341353}, "datetime": {"datetime": "2021-03-27 01:18:14", "elapsed": 360.655863, "delta": 2.31617}}
{"target": -1.4338914120880264, "params": {"model__colsample_bylevel": 0.3, "model__colsample_bynode": 0.3, "model__colsample_bytree": 1.0, "model__learning_rate": 0.3, "model__max_depth": 3.2607666799228996, "model__n_estimators": 22.219133909799332, "model__reg_lambda": 0.5277452727328146}, "datetime": {"datetime": "2021-03-27 01:18:16", "elapsed": 362.836041, "delta": 2.180178}}
{"target": -1.5359961289804482, "params": {"model__colsample_bylevel": 1.0, "model__colsample_bynode": 1.0, "model__colsample_bytree": 0.3, "model__learning_rate": 0.3, "model__max_depth": 2.0, "model__n_estimators": 18.560316858538112, "model__reg_lambda": 10.0}, "datetime": {"datetime": "2021-03-27 01:18:18", "elapsed": 364.734719, "delta": 1.898678}}
{"target": -1.4195531472847192, "params": {"model__colsample_bylevel": 0.3, "model__colsample_bynode": 1.0, "model__colsample_bytree": 1.0, "model__learning_rate": 0.3, "model__max_depth": 5.367190579196895, "model__n_estimators": 22.906920875579516, "model__reg_lambda": 6.212206875226933}, "datetime": {"datetime": "2021-03-27 01:18:21", "elapsed": 366.972577, "delta": 2.237858}}
{"target": -1.4811619466494608, "params": {"model__colsample_bylevel": 0.3, "model__colsample_bynode": 1.0, "model__colsample_bytree": 1.0, "model__learning_rate": 0.3, "model__max_depth": 8.0, "model__n_estimators": 17.926441263247217, "model__reg_lambda": 10.0}, "datetime": {"datetime": "2021-03-27 01:18:23", "elapsed": 368.950179, "delta": 1.977602}}
{"target": -1.3913346163334623, "params": {"model__colsample_bylevel": 1.0, "model__colsample_bynode": 0.3, "model__colsample_bytree": 0.3, "model__learning_rate": 0.3, "model__max_depth": 2.0, "model__n_estimators": 28.715806165909644, "model__reg_lambda": 1.9741478588844954}, "datetime": {"datetime": "2021-03-27 01:18:24", "elapsed": 370.831316, "delta": 1.881137}}
{"target": -1.436430095260342, "params": {"model__colsample_bylevel": 1.0, "model__colsample_bynode": 0.3, "model__colsample_bytree": 1.0, "model__learning_rate": 0.3, "model__max_depth": 4.194904626758346, "model__n_estimators": 19.743768127444973, "model__reg_lambda": 5.601731327794252}, "datetime": {"datetime": "2021-03-27 01:18:27", "elapsed": 372.981059, "delta": 2.149743}}
{"target": -1.4168637399561703, "params": {"model__colsample_bylevel": 1.0, "model__colsample_bynode": 0.3, "model__colsample_bytree": 0.3, "model__learning_rate": 0.3, "model__max_depth": 3.2192106924894732, "model__n_estimators": 28.16407272831756, "model__reg_lambda": 3.596079762220679}, "datetime": {"datetime": "2021-03-27 01:18:29", "elapsed": 374.895673, "delta": 1.914614}}
{"target": -1.4385268228277026, "params": {"model__colsample_bylevel": 0.3, "model__colsample_bynode": 1.0, "model__colsample_bytree": 1.0, "model__learning_rate": 0.3, "model__max_depth": 3.8798428739586157, "model__n_estimators": 21.084486256786015, "model__reg_lambda": 5.690731277536249}, "datetime": {"datetime": "2021-03-27 01:18:31", "elapsed": 377.033275, "delta": 2.137602}}
{"target": -1.48199883117408, "params": {"model__colsample_bylevel": 1.0, "model__colsample_bynode": 1.0, "model__colsample_bytree": 1.0, "model__learning_rate": 0.3, "model__max_depth": 8.0, "model__n_estimators": 22.213967678954994, "model__reg_lambda": 3.5492073513378477}, "datetime": {"datetime": "2021-03-27 01:18:34", "elapsed": 380.458664, "delta": 3.425389}}
{"target": -1.4634894421810043, "params": {"model__colsample_bylevel": 0.3, "model__colsample_bynode": 0.3, "model__colsample_bytree": 1.0, "model__learning_rate": 0.3, "model__max_depth": 8.0, "model__n_estimators": 21.845009425819217, "model__reg_lambda": 6.269789548120757}, "datetime": {"datetime": "2021-03-27 01:18:36", "elapsed": 382.66706, "delta": 2.208396}}
{"target": -1.4888040551996748, "params": {"model__colsample_bylevel": 0.3, "model__colsample_bynode": 0.3, "model__colsample_bytree": 1.0, "model__learning_rate": 0.3, "model__max_depth": 6.89014839625497, "model__n_estimators": 19.453856430107702, "model__reg_lambda": 4.261679318762632}, "datetime": {"datetime": "2021-03-27 01:18:39", "elapsed": 385.105891, "delta": 2.438831}}
{"target": -1.434650948713871, "params": {"model__colsample_bylevel": 0.3, "model__colsample_bynode": 0.3, "model__colsample_bytree": 1.0, "model__learning_rate": 0.1, "model__max_depth": 7.0329781054734415, "model__n_estimators": 30.0, "model__reg_lambda": 0.0}, "datetime": {"datetime": "2021-03-27 01:18:41", "elapsed": 387.326141, "delta": 2.22025}}
{"target": -1.3893221298138192, "params": {"model__colsample_bylevel": 0.35452955385174034, "model__colsample_bynode": 0.3271627438079752, "model__colsample_bytree": 0.3562374369436533, "model__learning_rate": 0.27369174003814223, "model__max_depth": 7.664940984085545, "model__n_estimators": 24.701916270832353, "model__reg_lambda": 1.9158516931311398}, "datetime": {"datetime": "2021-03-27 01:18:43", "elapsed": 389.682899, "delta": 2.356758}}
{"target": -1.4373104644480392, "params": {"model__colsample_bylevel": 1.0, "model__colsample_bynode": 0.3, "model__colsample_bytree": 1.0, "model__learning_rate": 0.3, "model__max_depth": 5.526073386305857, "model__n_estimators": 23.65237576938388, "model__reg_lambda": 7.579111263568596}, "datetime": {"datetime": "2021-03-27 01:18:46", "elapsed": 391.910904, "delta": 2.228005}}
{"target": -1.4934100533201211, "params": {"model__colsample_bylevel": 1.0, "model__colsample_bynode": 0.3, "model__colsample_bytree": 0.3, "model__learning_rate": 0.3, "model__max_depth": 5.712650596208302, "model__n_estimators": 20.080308377805277, "model__reg_lambda": 3.076139163050571}, "datetime": {"datetime": "2021-03-27 01:18:48", "elapsed": 394.006466, "delta": 2.095562}}
{"target": -1.4374483593807055, "params": {"model__colsample_bylevel": 1.0, "model__colsample_bynode": 1.0, "model__colsample_bytree": 0.3, "model__learning_rate": 0.3, "model__max_depth": 2.0, "model__n_estimators": 29.67017159024934, "model__reg_lambda": 0.0}, "datetime": {"datetime": "2021-03-27 01:18:50", "elapsed": 396.084127, "delta": 2.077661}}
{"target": -1.4420835226153332, "params": {"model__colsample_bylevel": 0.3, "model__colsample_bynode": 1.0, "model__colsample_bytree": 0.3, "model__learning_rate": 0.3, "model__max_depth": 8.0, "model__n_estimators": 24.89292107278584, "model__reg_lambda": 3.4353405514806385}, "datetime": {"datetime": "2021-03-27 01:18:52", "elapsed": 398.736068, "delta": 2.651941}}
{"target": -1.4499118065083587, "params": {"model__colsample_bylevel": 0.3, "model__colsample_bynode": 0.3, "model__colsample_bytree": 1.0, "model__learning_rate": 0.3, "model__max_depth": 4.0778072048072005, "model__n_estimators": 24.126555693459792, "model__reg_lambda": 10.0}, "datetime": {"datetime": "2021-03-27 01:18:55", "elapsed": 401.008607, "delta": 2.272539}}
{"target": -1.4747341886260616, "params": {"model__colsample_bylevel": 1.0, "model__colsample_bynode": 0.3, "model__colsample_bytree": 0.3, "model__learning_rate": 0.3, "model__max_depth": 8.0, "model__n_estimators": 24.108774617970592, "model__reg_lambda": 0.0}, "datetime": {"datetime": "2021-03-27 01:18:57", "elapsed": 403.537318, "delta": 2.528711}}
{"target": -1.4923204543311959, "params": {"model__colsample_bylevel": 0.3, "model__colsample_bynode": 0.3, "model__colsample_bytree": 0.3, "model__learning_rate": 0.3, "model__max_depth": 8.0, "model__n_estimators": 29.928741081418494, "model__reg_lambda": 8.925766126958822}, "datetime": {"datetime": "2021-03-27 01:18:59", "elapsed": 405.655381, "delta": 2.118063}}
{"target": -1.4670298221750537, "params": {"model__colsample_bylevel": 1.0, "model__colsample_bynode": 0.3, "model__colsample_bytree": 0.3, "model__learning_rate": 0.3, "model__max_depth": 3.7069027268684493, "model__n_estimators": 29.267391342984435, "model__reg_lambda": 8.935123267793168}, "datetime": {"datetime": "2021-03-27 01:19:02", "elapsed": 408.078395, "delta": 2.423014}}
{"target": -1.4306865698806404, "params": {"model__colsample_bylevel": 0.3, "model__colsample_bynode": 0.3, "model__colsample_bytree": 1.0, "model__learning_rate": 0.3, "model__max_depth": 4.589054112376009, "model__n_estimators": 27.751412528087194, "model__reg_lambda": 10.0}, "datetime": {"datetime": "2021-03-27 01:19:04", "elapsed": 410.322464, "delta": 2.244069}}
{"target": -1.4351474447688761, "params": {"model__colsample_bylevel": 1.0, "model__colsample_bynode": 0.3, "model__colsample_bytree": 1.0, "model__learning_rate": 0.3, "model__max_depth": 4.367151376327697, "model__n_estimators": 17.37208593683674, "model__reg_lambda": 1.715179884642514}, "datetime": {"datetime": "2021-03-27 01:19:06", "elapsed": 412.440344, "delta": 2.11788}}
{"target": -1.4786121148778046, "params": {"model__colsample_bylevel": 1.0, "model__colsample_bynode": 0.3, "model__colsample_bytree": 0.3, "model__learning_rate": 0.3, "model__max_depth": 3.4320339311499044, "model__n_estimators": 18.26532890247342, "model__reg_lambda": 0.0}, "datetime": {"datetime": "2021-03-27 01:19:08", "elapsed": 414.279655, "delta": 1.839311}}
{"target": -1.4818342696713365, "params": {"model__colsample_bylevel": 0.3, "model__colsample_bynode": 1.0, "model__colsample_bytree": 0.3, "model__learning_rate": 0.3, "model__max_depth": 8.0, "model__n_estimators": 16.325968005629957, "model__reg_lambda": 1.7649158014898119}, "datetime": {"datetime": "2021-03-27 01:19:10", "elapsed": 416.212857, "delta": 1.933202}}
{"target": -1.4661065963002433, "params": {"model__colsample_bylevel": 0.3, "model__colsample_bynode": 0.3, "model__colsample_bytree": 1.0, "model__learning_rate": 0.3, "model__max_depth": 8.0, "model__n_estimators": 25.454443650030655, "model__reg_lambda": 2.0170272700703715}, "datetime": {"datetime": "2021-03-27 01:19:12", "elapsed": 418.473419, "delta": 2.260562}}
{"target": -1.4140440605729276, "params": {"model__colsample_bylevel": 0.3, "model__colsample_bynode": 1.0, "model__colsample_bytree": 1.0, "model__learning_rate": 0.3, "model__max_depth": 8.0, "model__n_estimators": 27.712912880694628, "model__reg_lambda": 6.883850333000981}, "datetime": {"datetime": "2021-03-27 01:19:15", "elapsed": 421.094136, "delta": 2.620717}}
{"target": -1.4362330078896457, "params": {"model__colsample_bylevel": 0.3, "model__colsample_bynode": 1.0, "model__colsample_bytree": 1.0, "model__learning_rate": 0.3, "model__max_depth": 4.621172861882612, "model__n_estimators": 15.0, "model__reg_lambda": 0.0}, "datetime": {"datetime": "2021-03-27 01:19:17", "elapsed": 423.469971, "delta": 2.375835}}
{"target": -1.547632878009176, "params": {"model__colsample_bylevel": 0.3, "model__colsample_bynode": 1.0, "model__colsample_bytree": 0.3, "model__learning_rate": 0.3, "model__max_depth": 8.0, "model__n_estimators": 15.0, "model__reg_lambda": 10.0}, "datetime": {"datetime": "2021-03-27 01:19:19", "elapsed": 425.723173, "delta": 2.253202}}
{"target": -1.4177276712167415, "params": {"model__colsample_bylevel": 0.3, "model__colsample_bynode": 1.0, "model__colsample_bytree": 1.0, "model__learning_rate": 0.3, "model__max_depth": 8.0, "model__n_estimators": 24.47201400768016, "model__reg_lambda": 5.845693692781074}, "datetime": {"datetime": "2021-03-27 01:19:22", "elapsed": 428.460617, "delta": 2.737444}}
